Workbook

Sheet Resumen Ejecutivo
A1: GEN-MAMA-MX | Estimación de Costos — Plataforma Cloud GCP + Databricks
A2: Pipeline Bioinformático de Oncología de Precisión para Cáncer de Mama · Universidad de Sonora · 3 Años
A3: Fuentes: Investigación de mercado GCP/Databricks 2025 · Benchmarks NGS cloud (Franzoso 2025) · Fovus Boltz-1 $0.10/simulación · Vina GPU $0.95/10K dockings · Escala incremental 3 años
A5: INVERSIÓN TOTAL POR AÑO (USD) | B5: Año 1 (Fase Piloto) | C5: Año 2 (Expansión) | D5: Año 3 (Escala Plena) | E5: TOTAL 3 AÑOS | F5: ℹ️ Modelo incremental: Año 1 = 30% capacidad (~prototipo + 5 estados) Año 2 = 65% capacidad (~12 estados) Año 3 = 100% capacidad (~30K casos/año NGS)
B7: =Año1!C200 -> 492624 | C7: =Año2!C200 -> 630708 | D7: =Año3!C200 -> 783480 | E7: =B7+C7+D7 -> 1906812
A10: 📊 DESGLOSE POR CATEGORÍA — RESUMEN 3 AÑOS
A11: Categoría | B11: Descripción | C11: Año 1 USD | D11: Año 2 USD | E11: Año 3 USD | F11: Total 3 Años | G11: % del Total
A12: GCP — Cómputo GPU/CPU | B12: VMs GPU T4/A100 para Boltz-2, AlphaFold3, pipelines NGS | C12: =Año1!C50 -> 45 | D12: =Año2!C50 -> 98 | E12: =Año3!C50 -> 150 | F12: =C12+D12+E12 -> 293 | G12: =F12/F25 -> 0.020960011
A13: GCP — Cloud Storage | B13: GCS buckets Bronze/Silver/Gold · datos NGS, estructuras 3D | C13: =Año1!C60 -> 625 | D13: =Año2!C60 -> 625 | E13: =Año3!C60 -> 625 | F13: =C13+D13+E13 -> 1875 | G13: =F13/F25 -> 0.13412977
A14: GCP — Networking & API | B14: Egress, Load Balancing, API Gateway, IAP | C14: =Año1!C70 -> 1800 | D14: =Año2!C70 -> 3900 | E14: =Año3!C70 -> 6000 | F14: =C14+D14+E14 -> 11700 | G14: =F14/F25 -> 0.83696974
A15: GCP — OpenShift/GKE | B15: Microservicios, DevOps, CI/CD, Grafana monitoring | C15: =Año1!C80 -> 17 | D15: =Año2!C80 -> 37 | E15: =Año3!C80 -> 57 | F15: =C15+D15+E15 -> 111 | G15: =F15/F25 -> 0.0079404822
A16: GCP — BigQuery & BI | B16: SQL warehouse genómico, dashboards Looker Studio | C16: =Año1!C90 -> 0 | D16: =Año2!C90 -> 0 | E16: =Año3!C90 -> 0 | F16: =C16+D16+E16 -> 0 | G16: =F16/F25 -> 0
A17: GCP — Seguridad & IAM | B17: MFA, Cloud Armor, Secret Manager, HIPAA compliance | C17: =Año1!C100 -> 0 | D17: =Año2!C100 -> 0 | E17: =Año3!C100 -> 0 | F17: =C17+D17+E17 -> 0 | G17: =F17/F25 -> 0
A18: Databricks | B18: Medallion Delta (Bronze/Silver/Gold), MLOps, SQL Warehouse | C18: =Año1!C110 -> 0 | D18: =Año2!C110 -> 0 | E18: =Año3!C110 -> 0 | F18: =C18+D18+E18 -> 0 | G18: =F18/F25 -> 0
A19: Gemini LLM / RAG | B19: Gemini 1.5 Pro API, Vector Search, RAG científico | C19: =Año1!C120 -> 0 | D19: =Año2!C120 -> 0 | E19: =Año3!C120 -> 0 | F19: =C19+D19+E19 -> 0 | G19: =F19/F25 -> 0
A20: Antigravity IDE | B20: Licencias equipo desarrollo — 10 devs | C20: =Año1!C130 -> 0 | D20: =Año2!C130 -> 0 | E20: =Año3!C130 -> 0 | F20: =C20+D20+E20 -> 0 | G20: =F20/F25 -> 0
A21: Capacitación | B21: GCP, Databricks, IA Agéntica, RAG — 50 usuarios | C21: =Año1!C140 -> 0 | D21: =Año2!C140 -> 0 | E21: =Año3!C140 -> 0 | F21: =C21+D21+E21 -> 0 | G21: =F21/F25 -> 0
A22: Soporte Técnico | B22: Soporte L1/L2/L3 plataformas cloud y bioinformática | C22: =Año1!C150 -> 0 | D22: =Año2!C150 -> 0 | E22: =Año3!C150 -> 0 | F22: =C22+D22+E22 -> 0 | G22: =F22/F25 -> 0
A23: Servicios Profesionales | B23: Desarrollo, MLOps, DevOps, integración IMSS/ISSSTE | C23: =Año1!C160 -> 0 | D23: =Año2!C160 -> 0 | E23: =Año3!C160 -> 0 | F23: =C23+D23+E23 -> 0 | G23: =F23/F25 -> 0
A24: Licencias Software | B24: MongoDB Atlas, Nextflow Tower, GitHub Enterprise, otros | C24: =Año1!C170 -> 0 | D24: =Año2!C170 -> 0 | E24: =Año3!C170 -> 0 | F24: =C24+D24+E24 -> 0 | G24: =F24/F25 -> 0
A25: TOTAL PROYECTO GEN-MAMA-MX | C25: =SUM(C12:C24) -> 2487 | D25: =SUM(D12:D24) -> 4660 | E25: =SUM(E12:E24) -> 6832 | F25: =C25+D25+E25 -> 13979 | G25: 100.0%
A27: 🌎 PROYECTOS SIMILARES EN EL MUNDO — BENCHMARKS DE REFERENCIA
A28: • Genomics Core — Hospital Albert Einstein (Brasil, 2024) | B28: Pipeline NGS cloud AWS (Fargate+Batch). Procesamiento variantes oncológicas. SPOT instances para reducir costos. Presentado AWS Public Sector Symposium Brasília 2024.
A29: • Cancer Genomics Cloud (CGC) — Seven Bridges / NCI | B29: Plataforma multicloud (GCP/AWS/Azure) para pipelines TCGA. Costo promedio $50/tarea NGS. Recomiendan +30% buffer. Hosts TCGA-BRCA acceso abierto.
A30: • Sentieon/Parabricks NGS en GCP — Franzoso et al. 2025 | B30: Benchmark WES/WGS en GCP: VM 64-96 CPUs para Sentieon; GPU+48-64GB RAM para Parabricks. Referencia costo/muestra para análisis NGS clínico. Clinical & Translational Science 2025.
A31: • Boltz-1/2 en Fovus HPC Cloud (2025) | B31: $0.10/simulación Boltz-1 en GPU cloud. Vina GPU: $0.95/10,000 dockings. 30K casos/año × 15 genes × 11 fármacos = escala manejable con presupuesto proyectado.
A32: • INMEGEN / INCAn — México | B32: Secuenciador Illumina NovaSeq X. WES ~$300 USD/exoma. 26 proyectos activos en cáncer. Único posgrado de Alta Especialidad en Medicina de Precisión en Cáncer en México.
A33: • UK Biobank — Hail/Spark en GCP (PMC 2020) | B33: GWAS a escala de 500K genomas usando Hail sobre GCP. Demostró viabilidad de análisis distribuido genómico en cloud a costo-efectividad superior a HPC on-premise.

Sheet Año1
A1: GEN-MAMA-MX — Estimación de Costos Año1 | Factor de rampa: 30% | Casos NGS: 9,000 | Centros activos: 5
A2: USD por mes × 12 meses · Todos los costos en dólares americanos · Precios GCP us-central1 (Iowa) / Databricks on GCP 2025
A4: Componente / Recurso | B4: Especificación Técnica | C4: Costo/Mes USD | D4: Meses | E4: Total Anual USD | F4: Notas / Justificación
A5: ▌ 1. GCP — CÓMPUTO GPU / CPU (Boltz-2, AlphaFold3, NGS Pipelines)
A6: GPU Cluster — Boltz-2 / AlphaFold3 | B6: n1-standard-8 + NVIDIA T4 GPU · 66 GPU-hrs/mes · $1.40/hr · Predicción estructural 3D para 750 casos/mes × 15 genes objetivo | C6: 92 | D6: 12 | E6: =C6*D6 -> 1104 | F6: Ref: Fovus $0.10/sim; en GCP T4 ~20min/sim = $0.47/sim. Escala con casos NGS.
A7: GPU Premium — Lotes grandes (spot/preemptible) | B7: Preemptible T4: $0.35/hr · Ahorro 75% en lotes no urgentes · Docking masivo (Vina GPU): 8,250 pares receptor-ligando/mes | C7: 8 | D7: 12 | E7: =C7*D7 -> 96 | F7: Ref: Vina GPU $0.95/10K dockings. Mix preemptible/on-demand.
A8: CPU — Pipelines NGS (WES alignment + variant calling) | B8: n2-highcpu-32 · $0.94/hr · GATK/BWA/DeepVariant · 1,875 CPU-hrs/mes para 750 exomas/mes | C8: 1762 | D8: 12 | E8: =C8*D8 -> 21144 | F8: Ref: Franzoso 2025 — 64-96 CPUs por muestra WES en GCP. $300 WES cost incluye seq+análisis.
A9: CPU — Bioinformática General (MongoDB, ingesta, FASTA, QC) | B9: e2-standard-8 · $0.27/hr · Always-on para APIs, ingesta automatizada, QC pipelines | C9: 389 | D9: 12 | E9: =C9*D9 -> 4668 | F9: 2 instancias always-on: servidor APIs cBioPortal/UniProt, servidor MongoDB intermediario.
A10: Cloud Run — Microservicios (consulta resultados) | B10: Cloud Run autoscale · 2M requests/mes · 512MB RAM · API de resultados genomicos para investigadores LATAM | C10: 24 | D10: 12 | E10: =C10*D10 -> 288 | F10: Cloud Run: $0.40/M requests. Factor ramp aplicado.
A11: Subtotal — GCP Cómputo GPU/CPU | C11: =SUM(C6:C10) -> 2275 | D11: 12 | E11: =SUM(E6:E10) -> 27300
A12: ▌ 2. GCP — CLOUD STORAGE (Bronze/Silver/Gold + estructuras 3D)
A13: GCS Bronze — Datos RAW NGS (FASTQ, BAM, VCF) | B13: Standard Storage · 13.2 TB acumulado · $0.020/GB/mes · FASTQ 2×150bp WES (~5GB/muestra) + BAM + VCF raw | C13: 270 | D13: 12 | E13: =C13*D13 -> 3240 | F13: WES FASTQ ~5GB/muestra. Ciclo vida: 90 días standard → Nearline ($0.010). Retención 3 años.
A14: GCS Silver — Datos Procesados (mutaciones filtradas, FASTA) | B14: Nearline Storage · 1.98 TB · $0.010/GB/mes · JSON anotados, FASTA WT/mutados por variante, métricas pLDDT | C14: 20 | D14: 12 | E14: =C14*D14 -> 240 | F14: ~15% del volumen Bronze. Incluye top_variants.json, structural_metrics.json por cohorte.
A15: GCS Gold — Resultados Finales + Estructuras 3D | B15: Standard Storage · 0.20 TB estructuras CIF/PDB + 0.20 TB · $0.020/GB/mes · mmCIF Boltz-2, poses docking PDBQT, reportes HTML/PDF | C15: 8 | D15: 12 | E15: =C15*D15 -> 96 | F15: Estructuras 3D: ~5MB/variante CIF + poses docking. Acceso frecuente por investigadores.
A16: GCS Archival — Backup largo plazo | B16: Archive Storage · $0.0012/GB/mes · Snapshots mensuales completos | C16: 8 | D16: 12 | E16: =C16*D16 -> 96 | F16: 50% del Bronze archivado. Recuperación $0.05/GB. Para auditoría y reproducibilidad científica.
A17: Egress / Transfer | B17: Egress internet: $0.08/GB · Investigadores LATAM descargando reportes/estructuras · Estimado 75 GB/mes salida | C17: 6 | D17: 12 | E17: =C17*D17 -> 72 | F17: Reportes PDF ~2MB + estructuras CIF ~5MB × casos activos. CDN reduce costo.
A18: Subtotal — GCP Cloud Storage | C18: =SUM(C13:C17) -> 312 | D18: 12 | E18: =SUM(E13:E17) -> 3744
A19: ▌ 3. GCP — NETWORKING, API GATEWAY & SEGURIDAD
A20: Cloud Load Balancing + Cloud CDN | B20: Global HTTPS LB · $0.008/GB procesado · CDN para estructuras 3D y dashboards · 150 usuarios activos + aplicaciones móviles CONAFOR | C20: 120 | D20: 12 | E20: =C20*D20 -> 1440 | F20: LB: $18/mes base + $0.008/GB. CDN ahorra egress para assets estáticos (estructuras CIF).
A21: API Gateway / Cloud Endpoints | B21: API REST para integración IMSS/ISSSTE, apps móviles, intranet investigadores · 10M calls/mes estimado en escala plena | C21: 90 | D21: 12 | E21: =C21*D21 -> 1080 | F21: $3.50/M API calls primeros 2M, luego $1.50/M. Incluye quota management y API keys por institución.
A22: Cloud Armor (WAF + DDoS) | B22: Protección WAF para APIs genómicas · HIPAA compliance · $5/política + $0.75/M requests protegidas | C22: 60 | D22: 12 | E22: =C22*D22 -> 720 | F22: Dato médico sensible requiere protección WAF. HIPAA BAA con GCP.
A23: VPC + Interconnect (privado centros investigación) | B23: Cloud VPN HA para conexión IMSS/ISSSTE/INMEGEN · $0.05/hr por túnel | C23: 72 | D23: 12 | E23: =C23*D23 -> 864 | F23: 2 túneles HA VPN: UNISON Hermosillo + INMEGEN CDMX. Transferencia segura muestras NGS.
A24: Subtotal — GCP Networking & API | C24: =SUM(C20:C23) -> 342 | D24: 12 | E24: =SUM(E20:E23) -> 4104
A25: ▌ 4. GCP — OpenShift / GKE · DevOps · MLOps · Monitoreo Grafana
A26: GKE (Google Kubernetes Engine) — Cluster Microservicios | B26: 3 nodos e2-standard-4 (always-on) + autoscale 1-8 nodos · Microservicios: consulta resultados, API genómica, portal investigadores LATAM | C26: 361 | D26: 12 | E26: =C26*D26 -> 4332 | F26: e2-standard-4: $0.134/hr. GKE management fee: $72/mes. Istio service mesh incluido.
A27: OpenShift on GCP (ROSA equivalent) — Apps Institucionales | B27: OpenShift 4.x en GCP · Control plane managed · Workers n2-standard-4 · Apps intranet IMSS/ISSSTE + portal genómico + app móvil backend | C27: 240 | D27: 12 | E27: =C27*D27 -> 2880 | F27: OpenShift Enterprise: ~$0.11/vCPU/hr. 4 workers × 4 vCPU = ~$1,267/mes base. Factor ramp.
A28: Cloud Build + Artifact Registry (CI/CD) | B28: CI/CD para pipelines bioinformáticos + microservicios · 120 builds/mes · Docker images · GitHub Enterprise integration | C28: 45 | D28: 12 | E28: =C28*D28 -> 540 | F28: Cloud Build: primeros 120min/día gratis. Artifact Registry: $0.10/GB. GitHub Enterprise separado.
A29: Vertex AI Pipelines (MLOps — Kubeflow Pipelines) | B29: Orquestación pipelines NGS, entrenamiento modelos variantes, inferencia batch · 5 pipelines paralelos por centro | C29: 75 | D29: 12 | E29: =C29*D29 -> 900 | F29: Vertex AI Pipelines: $0.03/vCPU-hr + $0.005/GB-hr. Reemplaza Airflow self-managed.
A30: Vertex AI Model Registry + Endpoint (modelo variantes) | B30: Registro versiones modelos ML (clasificación VUS, predicción afinidad) · Endpoints para inferencia online <500ms · Explicabilidad integrada | C30: 90 | D30: 12 | E30: =C30*D30 -> 1080 | F30: Vertex AI Prediction: $0.051/hr nodo n1-standard-4. 1 endpoint always-on + batch prediction.
A31: Grafana Cloud (monitoreo integral) | B31: Grafana Cloud Pro · Métricas GCP + Databricks + pipelines Nextflow · Dashboards: GPU utilization, pipeline success rate, costo/muestra, alertas | C31: 60 | D31: 12 | E31: =C31*D31 -> 720 | F31: Grafana Cloud Pro: $299/mes (50K métricas). Integra con Cloud Monitoring via plugin. Dashboards: NGS throughput, docking queue, GPU %, Databricks job latency.
A32: Cloud Monitoring + Logging + Trace | B32: Operations Suite (stackdriver) · Logs retención 30 días · Custom metrics pipelines bioinformáticos · Budget alerts | C32: 45 | D32: 12 | E32: =C32*D32 -> 540 | F32: First 50GB logs/mes gratis. Custom metrics: $0.10/metric/mes. Trace: $0.20/M spans.
A33: Subtotal — OpenShift/GKE + DevOps + MLOps + Grafana | C33: =SUM(C26:C32) -> 916 | D33: 12 | E33: =SUM(E26:E32) -> 10992
A34: ▌ 5. GCP — BigQuery (SQL Warehouse Genómico) + Looker Studio Dashboards
A35: BigQuery — SQL Warehouse Genómico | B35: Almacén central: mutaciones somáticas, variantes anotadas, métricas docking · 18.0 TB activo · $5/TB consultas · Storage $0.020/GB/mes | C35: 549 | D35: 12 | E35: =C35*D35 -> 6588 | F35: BQ free: 10GB storage + 1TB queries/mes. Superado a partir Año 2. Flat-rate $2,000/mes considerado Año 3 si queries >10TB/mes.
A36: Looker Studio Pro — Dashboards Investigadores | B36: Dashboards interactivos: distribución variantes, heatmap docking, progreso cohorte por centro · 150 usuarios · $9/usuario/mes (Pro) | C36: 135 | D36: 12 | E36: =C36*D36 -> 1620 | F36: Looker Studio Pro $9/user/mes. Free tier suficiente para vistas básicas. Pro para BI embedido en portal investigadores y exportación a apps intranet.
A37: DataFlow (ETL ingesta datos clínicos) | B37: Ingesta automatizada: cBioPortal API, GDC API, INMEGEN, IMSS/ISSSTE · Streaming + batch · Procesamiento JSON → BigQuery | C37: 60 | D37: 12 | E37: =C37*D37 -> 720 | F37: Dataflow: $0.056/vCPU-hr + $0.003756/GB-hr. Pipelines Nextflow complementan Dataflow.
A38: Subtotal — BigQuery + Looker Studio | C38: =SUM(C35:C37) -> 744 | D38: 12 | E38: =SUM(E35:E37) -> 8928
A39: ▌ 6. GCP — SEGURIDAD, IAM & COMPLIANCE (MFA, HIPAA, LGPD México)
A40: Cloud Identity + MFA (Autenticación Multifactor) | B40: Cloud Identity Premium · 150 usuarios investigadores + 15 admins · MFA: Google Authenticator / hardware keys · SSO SAML institucional | C40: 990 | D40: 12 | E40: =C40*D40 -> 11880 | F40: Cloud Identity Premium: $6/usuario/mes. 165 usuarios totales (150 inv + 15 admin). MFA obligatorio para acceso a datos genómicos. LGPD México + HIPAA BAA.
A41: Secret Manager + KMS (cifrado llaves API) | B41: Gestión segura de API keys: ChEMBL, UniProt, cBioPortal, GDC, INMEGEN · KMS para cifrado datos en reposo (datos pacientes) | C41: 80 | D41: 12 | E41: =C41*D41 -> 960 | F41: Secret Manager: $0.06/secret/mes + $0.03/10K accesos. KMS: $0.06/llave/mes. Cifrado AES-256 datos NGS. Requerido para BAA con GCP y cumplimiento NOM-024.
A42: Cloud DLP (Data Loss Prevention — datos pacientes) | B42: Inspección automática PII en outputs: nombres, IDs, datos clínicos · Previene exposición accidental de datos de pacientes | C42: 30 | D42: 12 | E42: =C42*D42 -> 360 | F42: Cloud DLP: $0.001/GB inspeccionado. Crítico para LGPD México y privacidad datos oncológicos.
A43: Access Context Manager + VPC Service Controls | B43: Perímetro de seguridad para datos genómicos · Solo acceso desde IPs autorizadas · Audit logs completos para trazabilidad científica | C43: 24 | D43: 12 | E43: =C43*D43 -> 288 | F43: VPC SC previene exfiltración datos. Requerido para datos TCGA y datos clínicos IMSS/ISSSTE.
A44: Subtotal — Seguridad & Compliance | C44: =SUM(C40:C43) -> 1124 | D44: 12 | E44: =SUM(E40:E43) -> 13488
A45: ▌ 7. DATABRICKS on GCP — Medallion Delta (Bronze/Silver/Gold) + MLOps + SQL Warehouse
A46: Databricks — Jobs Compute (pipelines ETL Medallion) | B46: Delta Lake Bronze→Silver→Gold · ETL mutaciones, variantes anotadas, docking scores · ~375 DBU/mes · $0.15/DBU (Jobs Compute) | C46: 56 | D46: 12 | E46: =C46*D46 -> 672 | F46: Medallion Bronze: ingesta raw JSON/VCF. Silver: normalización, filtros Tier 1/2/3. Gold: cohorte analítica, variantes × fármaco, métricas por centro. Delta tables con ACID transactions para reproducibilidad.
A47: Databricks — SQL Warehouse (consultas investigadores) | B47: SQL Serverless Warehouse · 10 DBU/hr mínimo · Consultas ad-hoc sobre cohortes · Conexión Power BI / Looker para dashboards científicos | C47: 116 | D47: 12 | E47: =C47*D47 -> 1392 | F47: SQL Warehouse Serverless: $0.22/DBU. 8hr/día uso activo × 22 días. Auto-suspend 10 min. Acceso 150 investigadores para consultas SQL genómicas.
A48: Databricks — All-Purpose Cluster (exploración científica) | B48: Jupyter notebooks interactivos · Análisis exploratorio cohortes · Visualizaciones Plotly · 4 clusters × investigadores principales | C48: 169 | D48: 12 | E48: =C48*D48 -> 2028 | F48: All-Purpose: $0.40/DBU. 4 DBU/hr por cluster. 4hr/día análisis interactivo. Glow library para análisis variantes genómicas en Spark.
A49: Databricks — MLflow (tracking experimentos ML) | B49: Tracking automático: hiperparámetros modelos variantes, métricas RMSD, scores docking Vina, comparativas WT vs Mutada por cohorte | C49: 60 | D49: 12 | E49: =C49*D49 -> 720 | F49: MLflow Managed: incluido en licencia Databricks. Modelo registry para versionar clasificadores VUS → Patogénica.
A50: Databricks — Delta Sharing (colaboración LATAM) | B50: Compartir Delta tables con investigadores latinoamericanos sin mover datos · 15 investigadores externos (read-only access) · Auditoría completa | C50: 45 | D50: 12 | E50: =C50*D50 -> 540 | F50: Delta Sharing open protocol. Investigadores Argentina, Chile, Colombia pueden consultar cohorte mexicana sin descarga. Governance con Unity Catalog.
A51: Databricks — Unity Catalog (gobernanza datos) | B51: Catálogo central: tablas genómicas, modelos ML, notebooks científicos · Control acceso por institución · Lineage de datos | C51: 90 | D51: 12 | E51: =C51*D51 -> 1080 | F51: Unity Catalog: incluido en licencias Premium. Esencial para cumplimiento científico (reproducibilidad) y regulatorio (LGPD/NOM-024).
A52: Subtotal — Databricks on GCP — Medallion + MLOps | C52: =SUM(C46:C51) -> 536 | D52: 12 | E52: =SUM(E46:E51) -> 6432
A53: ▌ 8. GEMINI LLM + RAG — Asistente Científico para Equipos de Investigación
A54: Gemini 1.5 Pro API — RAG Científico | B54: RAG sobre literatura oncológica, ClinVar, OncoKB, ChEMBL · Consultas: '¿Qué fármacos existen para PIK3CA H1047R?' · Estimado 1,000 queries/mes × investigadores | C54: 4 | D54: 12 | E54: =C54*D54 -> 48 | F54: Gemini 1.5 Pro: $0.0125/1K tokens input, $0.0375/1K output. Query típico ~2K tokens. RAG base: PubMed oncología, FDA labels, ClinVar.
A55: Vertex AI Vector Search (embeddings RAG) | B55: Índice vectorial literatura científica oncológica · 50K documentos: papers PubMed, ficha técnica fármacos, reportes ClinVar · Actualización mensual automática | C55: 120 | D55: 12 | E55: =C55*D55 -> 1440 | F55: Vertex AI Vector Search: $0.036/hr por nodo. 1 nodo suficiente para 50K docs. Embeddings: text-embedding-004 $0.025/M tokens.
A56: Gemini — Generación Reportes Clínicos Automatizada | B56: Auto-generación reportes por variante: resumen ejecutivo, métricas estructurales, candidatos farmacológicos, recomendación clínica · PDF/HTML | C56: 1 | D56: 12 | E56: =C56*D56 -> 12 | F56: Reporte por variante ~5K tokens output. Gemini 1.5 Flash $0.0001875/1K tokens output para reportes batch económicos.
A57: Subtotal — Gemini LLM + RAG | C57: =SUM(C54:C56) -> 125 | D57: 12 | E57: =SUM(E54:E56) -> 1500
A58: ▌ 9. ANTIGRAVITY IDE — Licencias Equipo Desarrollo & Soporte
A59: Antigravity IDE — Licencias Desarrolladores | B59: 10 licencias desarrolladores/bioinformáticos · Planning Mode + Gemini 3 Pro · Desarrollo pipeline GEN-MAMA-MX, microservicios, MLOps | C59: 300 | D59: 12 | E59: =C59*D59 -> 3600 | F59: Antigravity IDE (Google): ~$30/usuario/mes estimado. Usado en prototipo actual (Claude Sonnet + Gemini 3 Pro). Acelera desarrollo 4x vs IDE tradicional según documentación proyecto.
A60: Capacitación IA Agéntica + LLM RAGs en Gemini | B60: Workshop 40 horas: agentes IA, RAG científico, prompt engineering para oncología · 50 usuarios (investigadores + soporte técnico) | C60: 625 | D60: 12 | E60: =C60*D60 -> 7500 | F60: $150/usuario por workshop completo. Google Cloud Skills Boost + instructor especializado. Incluye: Gemini API, Vertex AI, RAG construction, agentes para análisis genómico.
A61: Subtotal — Antigravity IDE + Capacitación IA | C61: =SUM(C59:C60) -> 925 | D61: 12 | E61: =SUM(E59:E60) -> 11100
A62: ▌ 10. CAPACITACIÓN — GCP, Databricks, Pipeline GEN-MAMA-MX (50 usuarios)
A63: GCP Fundamentals + Bioinformatics on GCP | B63: 50 usuarios · Google Cloud Skills Boost · 20 cursos especializados · Bioinformatics on GCP, Vertex AI, BigQuery genomics | C63: 1250 | D63: 12 | E63: =C63*D63 -> 15000 | F63: $300/usuario cloud training completo (año). Google for Startups reduce 30% para académicos. Certificación: Professional Data Engineer recomendada para equipo técnico.
A64: Databricks Fundamentals + Genomics Lakehouse | B64: 50 usuarios · Databricks Academy · Delta Lake, MLflow, Unity Catalog · Especialización: Glow genomics library, VariantSpark | C64: 833 | D64: 12 | E64: =C64*D64 -> 9996 | F64: $200/usuario Databricks Academy (año). Incluye: Databricks Certified Associate. Genomics Lakehouse track: Delta tables para VCF/FASTQ processing.
A65: Pipeline GEN-MAMA-MX — Capacitación Interna | B65: Taller personalizado 32 hrs: uso de la plataforma, interpretación resultados docking, flujo biopsia→reporte, validación clínica · Para oncólogos y bioinformáticos | C65: 333 | D65: 12 | E65: =C65*D65 -> 3996 | F65: $80/usuario taller interno con instructor UNISON. Incluye: demo con TCGA-BRCA, casos reales PIK3CA H1047R, interpretación alpelisib.
A66: Subtotal — Capacitación GCP + Databricks + Pipeline | C66: =SUM(C63:C65) -> 2416 | D66: 12 | E66: =SUM(E63:E65) -> 28992
A67: ▌ 11. SOPORTE TÉCNICO — Plataformas Cloud + Bioinformática
A68: GCP Premium Support | B68: Premium Support GCP · SLA 1hr respuesta P1 · TAM dedicado · Revisión arquitectura bioinformática trimestral | C68: 450 | D68: 12 | E68: =C68*D68 -> 5400 | F68: GCP Premium Support: máx(3% gasto mensual, $1,500). Incluye Technical Account Manager. Requerido para SLA productivo con datos clínicos.
A69: Databricks Enterprise Support | B69: Enterprise Support Databricks · 24/7 · SLA 4hr P1 · Expert sessions MLOps y genomics Lakehouse | C69: 240 | D69: 12 | E69: =C69*D69 -> 2880 | F69: Databricks Enterprise Support: incluido en licencia Enterprise. Costo separado si se usa Pay-as-you-go: ~$800/mes.
A70: Soporte Bioinformático Especializado (L2/L3) | B70: 2 bioinformáticos cloud (FTE 0.5) · Soporte pipelines Nextflow, GATK, Boltz-2, AutoDock Vina · Troubleshooting NGS análisis | C70: 1800 | D70: 12 | E70: =C70*D70 -> 21600 | F70: Bioinformático cloud LATAM: ~$3,000/mes (medio tiempo). Alternativa: contrato soporte con Hospital Albert Einstein / Varsomics Brasil.
A71: Soporte Usuarios Investigadores (helpdesk) | B71: L1 helpdesk para 150 investigadores · Portal resultados, apps móviles · Documentación, videos tutoriales, FAQ genómico | C71: 150 | D71: 12 | E71: =C71*D71 -> 1800 | F71: 0.5 FTE helpdesk + base conocimiento Confluence. SLA 24hr para investigadores, 4hr para oncólogos IMSS en producción.
A72: Subtotal — Soporte Técnico | C72: =SUM(C68:C71) -> 2640 | D72: 12 | E72: =SUM(E68:E71) -> 31680
A73: ▌ 12. SERVICIOS PROFESIONALES — Desarrollo, Integración, MLOps
A74: Desarrollo Pipeline Bioinformático (DevOps/Bioinformática) | B74: Equipo 3 devs × 3 años · Nextflow pipeline manager, integración cBioPortal+GDC+INMEGEN, portal investigadores LATAM | C74: 15000 | D74: 12 | E74: =C74*D74 -> 180000 | F74: $5,000/mes por desarrollador bioinformático senior LATAM. Incluye: pipelines Nextflow WDL, API integrations, frontend portal, CI/CD.
A75: MLOps Engineering (Vertex AI + Databricks) | B75: 1.5 FTE MLOps · Kubeflow Pipelines, MLflow tracking, model versioning, A/B testing modelos variantes, monitoreo drift | C75: 9000 | D75: 12 | E75: =C75*D75 -> 108000 | F75: $6,000/mes MLOps engineer senior. Entregables: pipelines entrenamiento automático, inferencia batch 30K casos/año.
A76: Integración IMSS/ISSSTE/INMEGEN | B76: Consultoría integración sistemas institucionales · API FHIR HL7 · NOM-024 cumplimiento · Piloto Hermosillo 6 meses | C76: 2000 | D76: 12 | E76: =C76*D76 -> 24000 | F76: $2,000/mes consultoría integración HL7/FHIR. Requerido para transferir datos NGS IMSS → plataforma GCP. NOM-024-SSA3.
A77: Desarrollo App Móvil + Intranet Investigadores | B77: App iOS/Android para acceso resultados en campo · Portal web intranet para oncólogos · React Native + microservicios GKE | C77: 900 | D77: 12 | E77: =C77*D77 -> 10800 | F77: $3,000/mes mantenimiento app post-desarrollo inicial. Año 1: desarrollo activo. Año 2-3: mantenimiento + features.
A78: Subtotal — Servicios Profesionales | C78: =SUM(C74:C77) -> 26900 | D78: 12 | E78: =SUM(E74:E77) -> 322800
A79: ▌ 13. LICENCIAS SOFTWARE — MongoDB Atlas, Nextflow Tower, GitHub Enterprise, otros
A80: MongoDB Atlas (nube — fase análisis) | B80: M10 cluster · 2GB RAM · Almacén intermedio ingesta · Colecciones: mutations, top_variants, fasta_sequences | C80: 17 | D80: 12 | E80: =C80*D80 -> 204 | F80: MongoDB Atlas M10: $57/mes. Reemplaza MongoDB local para ambiente cloud. Solo fase análisis; Gold layer usa BigQuery + Delta Lake.
A81: Nextflow Tower (orquestación pipelines NGS) | B81: Nextflow Tower Pro · Orquestación visual pipelines NGS en GCP · 5 pipelines paralelos · Integración GitHub | C81: 150 | D81: 12 | E81: =C81*D81 -> 1800 | F81: Nextflow Tower Pro: ~$500/mes (10 workspaces). Workflows: GATK WES, Boltz-2 batch, docking paralelo, QC reports.
A82: GitHub Enterprise (control versiones + CI/CD) | B82: 50 licencias · Actions ilimitadas · Advanced Security · Dependabot para dependencias bioinformáticas | C82: 1050 | D82: 12 | E82: =C82*D82 -> 12600 | F82: GitHub Enterprise: $21/usuario/mes. Repositorios: pipeline GEN-MAMA-MX, microservicios, infraestructura IaC (Terraform).
A83: Tableau / PowerBI (alternativa Looker Studio) | B83: Dashboards avanzados para presentaciones institucionales · 20 licencias para PIs y administradores | C83: 420 | D83: 12 | E83: =C83*D83 -> 5040 | F83: Tableau Creator: $70/usuario/mes. Alternativa a Looker Studio Pro para reportes ejecutivos CONACYT, Google.org, publicaciones científicas.
A84: Jira + Confluence (gestión proyecto científico) | B84: Backlog bioinformático, sprints, documentación técnica · 20 usuarios equipo desarrollo + PIs | C84: 160 | D84: 12 | E84: =C84*D84 -> 1920 | F84: Atlassian Cloud Standard: $8.15/usuario/mes. Usado en prototipo (ver GENMAMAMX_Backlog_Prototipo.docx).
A85: Subtotal — Licencias Software Adicionales | C85: =SUM(C80:C84) -> 1797 | D85: 12 | E85: =SUM(E80:E84) -> 21564
A87: TOTAL Año1 — GEN-MAMA-MX | C87: =(E11+E18+E24+E33+E38+E44+E52+E57+E61+E66+E72+E78+E85)/12 -> 41052 | D87: 12 | E87: =E11+E18+E24+E33+E38+E44+E52+E57+E61+E66+E72+E78+E85 -> 492624 | F87: Factor ramp: 30% | Casos NGS/año: 9,000 | Centros: 5
C200: =E87 -> 492624

Sheet Año2
A1: GEN-MAMA-MX — Estimación de Costos Año2 | Factor de rampa: 65% | Casos NGS: 19,500 | Centros activos: 12
A2: USD por mes × 12 meses · Todos los costos en dólares americanos · Precios GCP us-central1 (Iowa) / Databricks on GCP 2025
A4: Componente / Recurso | B4: Especificación Técnica | C4: Costo/Mes USD | D4: Meses | E4: Total Anual USD | F4: Notas / Justificación
A5: ▌ 1. GCP — CÓMPUTO GPU / CPU (Boltz-2, AlphaFold3, NGS Pipelines)
A6: GPU Cluster — Boltz-2 / AlphaFold3 | B6: n1-standard-8 + NVIDIA T4 GPU · 142 GPU-hrs/mes · $1.40/hr · Predicción estructural 3D para 1,625 casos/mes × 15 genes objetivo | C6: 199 | D6: 12 | E6: =C6*D6 -> 2388 | F6: Ref: Fovus $0.10/sim; en GCP T4 ~20min/sim = $0.47/sim. Escala con casos NGS.
A7: GPU Premium — Lotes grandes (spot/preemptible) | B7: Preemptible T4: $0.35/hr · Ahorro 75% en lotes no urgentes · Docking masivo (Vina GPU): 17,875 pares receptor-ligando/mes | C7: 17 | D7: 12 | E7: =C7*D7 -> 204 | F7: Ref: Vina GPU $0.95/10K dockings. Mix preemptible/on-demand.
A8: CPU — Pipelines NGS (WES alignment + variant calling) | B8: n2-highcpu-32 · $0.94/hr · GATK/BWA/DeepVariant · 4,062 CPU-hrs/mes para 1,625 exomas/mes | C8: 3818 | D8: 12 | E8: =C8*D8 -> 45816 | F8: Ref: Franzoso 2025 — 64-96 CPUs por muestra WES en GCP. $300 WES cost incluye seq+análisis.
A9: CPU — Bioinformática General (MongoDB, ingesta, FASTA, QC) | B9: e2-standard-8 · $0.27/hr · Always-on para APIs, ingesta automatizada, QC pipelines | C9: 389 | D9: 12 | E9: =C9*D9 -> 4668 | F9: 2 instancias always-on: servidor APIs cBioPortal/UniProt, servidor MongoDB intermediario.
A10: Cloud Run — Microservicios (consulta resultados) | B10: Cloud Run autoscale · 2M requests/mes · 512MB RAM · API de resultados genomicos para investigadores LATAM | C10: 52 | D10: 12 | E10: =C10*D10 -> 624 | F10: Cloud Run: $0.40/M requests. Factor ramp aplicado.
A11: Subtotal — GCP Cómputo GPU/CPU | C11: =SUM(C6:C10) -> 4475 | D11: 12 | E11: =SUM(E6:E10) -> 53700
A12: ▌ 2. GCP — CLOUD STORAGE (Bronze/Silver/Gold + estructuras 3D)
A13: GCS Bronze — Datos RAW NGS (FASTQ, BAM, VCF) | B13: Standard Storage · 61.9 TB acumulado · $0.020/GB/mes · FASTQ 2×150bp WES (~5GB/muestra) + BAM + VCF raw | C13: 1268 | D13: 12 | E13: =C13*D13 -> 15216 | F13: WES FASTQ ~5GB/muestra. Ciclo vida: 90 días standard → Nearline ($0.010). Retención 3 años.
A14: GCS Silver — Datos Procesados (mutaciones filtradas, FASTA) | B14: Nearline Storage · 9.28 TB · $0.010/GB/mes · JSON anotados, FASTA WT/mutados por variante, métricas pLDDT | C14: 95 | D14: 12 | E14: =C14*D14 -> 1140 | F14: ~15% del volumen Bronze. Incluye top_variants.json, structural_metrics.json por cohorte.
A15: GCS Gold — Resultados Finales + Estructuras 3D | B15: Standard Storage · 0.93 TB estructuras CIF/PDB + 0.93 TB · $0.020/GB/mes · mmCIF Boltz-2, poses docking PDBQT, reportes HTML/PDF | C15: 38 | D15: 12 | E15: =C15*D15 -> 456 | F15: Estructuras 3D: ~5MB/variante CIF + poses docking. Acceso frecuente por investigadores.
A16: GCS Archival — Backup largo plazo | B16: Archive Storage · $0.0012/GB/mes · Snapshots mensuales completos | C16: 38 | D16: 12 | E16: =C16*D16 -> 456 | F16: 50% del Bronze archivado. Recuperación $0.05/GB. Para auditoría y reproducibilidad científica.
A17: Egress / Transfer | B17: Egress internet: $0.08/GB · Investigadores LATAM descargando reportes/estructuras · Estimado 162 GB/mes salida | C17: 13 | D17: 12 | E17: =C17*D17 -> 156 | F17: Reportes PDF ~2MB + estructuras CIF ~5MB × casos activos. CDN reduce costo.
A18: Subtotal — GCP Cloud Storage | C18: =SUM(C13:C17) -> 1452 | D18: 12 | E18: =SUM(E13:E17) -> 17424
A19: ▌ 3. GCP — NETWORKING, API GATEWAY & SEGURIDAD
A20: Cloud Load Balancing + Cloud CDN | B20: Global HTTPS LB · $0.008/GB procesado · CDN para estructuras 3D y dashboards · 150 usuarios activos + aplicaciones móviles CONAFOR | C20: 260 | D20: 12 | E20: =C20*D20 -> 3120 | F20: LB: $18/mes base + $0.008/GB. CDN ahorra egress para assets estáticos (estructuras CIF).
A21: API Gateway / Cloud Endpoints | B21: API REST para integración IMSS/ISSSTE, apps móviles, intranet investigadores · 10M calls/mes estimado en escala plena | C21: 195 | D21: 12 | E21: =C21*D21 -> 2340 | F21: $3.50/M API calls primeros 2M, luego $1.50/M. Incluye quota management y API keys por institución.
A22: Cloud Armor (WAF + DDoS) | B22: Protección WAF para APIs genómicas · HIPAA compliance · $5/política + $0.75/M requests protegidas | C22: 130 | D22: 12 | E22: =C22*D22 -> 1560 | F22: Dato médico sensible requiere protección WAF. HIPAA BAA con GCP.
A23: VPC + Interconnect (privado centros investigación) | B23: Cloud VPN HA para conexión IMSS/ISSSTE/INMEGEN · $0.05/hr por túnel | C23: 72 | D23: 12 | E23: =C23*D23 -> 864 | F23: 2 túneles HA VPN: UNISON Hermosillo + INMEGEN CDMX. Transferencia segura muestras NGS.
A24: Subtotal — GCP Networking & API | C24: =SUM(C20:C23) -> 657 | D24: 12 | E24: =SUM(E20:E23) -> 7884
A25: ▌ 4. GCP — OpenShift / GKE · DevOps · MLOps · Monitoreo Grafana
A26: GKE (Google Kubernetes Engine) — Cluster Microservicios | B26: 3 nodos e2-standard-4 (always-on) + autoscale 1-8 nodos · Microservicios: consulta resultados, API genómica, portal investigadores LATAM | C26: 361 | D26: 12 | E26: =C26*D26 -> 4332 | F26: e2-standard-4: $0.134/hr. GKE management fee: $72/mes. Istio service mesh incluido.
A27: OpenShift on GCP (ROSA equivalent) — Apps Institucionales | B27: OpenShift 4.x en GCP · Control plane managed · Workers n2-standard-4 · Apps intranet IMSS/ISSSTE + portal genómico + app móvil backend | C27: 520 | D27: 12 | E27: =C27*D27 -> 6240 | F27: OpenShift Enterprise: ~$0.11/vCPU/hr. 4 workers × 4 vCPU = ~$1,267/mes base. Factor ramp.
A28: Cloud Build + Artifact Registry (CI/CD) | B28: CI/CD para pipelines bioinformáticos + microservicios · 120 builds/mes · Docker images · GitHub Enterprise integration | C28: 98 | D28: 12 | E28: =C28*D28 -> 1176 | F28: Cloud Build: primeros 120min/día gratis. Artifact Registry: $0.10/GB. GitHub Enterprise separado.
A29: Vertex AI Pipelines (MLOps — Kubeflow Pipelines) | B29: Orquestación pipelines NGS, entrenamiento modelos variantes, inferencia batch · 12 pipelines paralelos por centro | C29: 390 | D29: 12 | E29: =C29*D29 -> 4680 | F29: Vertex AI Pipelines: $0.03/vCPU-hr + $0.005/GB-hr. Reemplaza Airflow self-managed.
A30: Vertex AI Model Registry + Endpoint (modelo variantes) | B30: Registro versiones modelos ML (clasificación VUS, predicción afinidad) · Endpoints para inferencia online <500ms · Explicabilidad integrada | C30: 195 | D30: 12 | E30: =C30*D30 -> 2340 | F30: Vertex AI Prediction: $0.051/hr nodo n1-standard-4. 1 endpoint always-on + batch prediction.
A31: Grafana Cloud (monitoreo integral) | B31: Grafana Cloud Pro · Métricas GCP + Databricks + pipelines Nextflow · Dashboards: GPU utilization, pipeline success rate, costo/muestra, alertas | C31: 130 | D31: 12 | E31: =C31*D31 -> 1560 | F31: Grafana Cloud Pro: $299/mes (50K métricas). Integra con Cloud Monitoring via plugin. Dashboards: NGS throughput, docking queue, GPU %, Databricks job latency.
A32: Cloud Monitoring + Logging + Trace | B32: Operations Suite (stackdriver) · Logs retención 30 días · Custom metrics pipelines bioinformáticos · Budget alerts | C32: 98 | D32: 12 | E32: =C32*D32 -> 1176 | F32: First 50GB logs/mes gratis. Custom metrics: $0.10/metric/mes. Trace: $0.20/M spans.
A33: Subtotal — OpenShift/GKE + DevOps + MLOps + Grafana | C33: =SUM(C26:C32) -> 1792 | D33: 12 | E33: =SUM(E26:E32) -> 21504
A34: ▌ 5. GCP — BigQuery (SQL Warehouse Genómico) + Looker Studio Dashboards
A35: BigQuery — SQL Warehouse Genómico | B35: Almacén central: mutaciones somáticas, variantes anotadas, métricas docking · 39.0 TB activo · $5/TB consultas · Storage $0.020/GB/mes | C35: 1189 | D35: 12 | E35: =C35*D35 -> 14268 | F35: BQ free: 10GB storage + 1TB queries/mes. Superado a partir Año 2. Flat-rate $2,000/mes considerado Año 3 si queries >10TB/mes.
A36: Looker Studio Pro — Dashboards Investigadores | B36: Dashboards interactivos: distribución variantes, heatmap docking, progreso cohorte por centro · 150 usuarios · $9/usuario/mes (Pro) | C36: 702 | D36: 12 | E36: =C36*D36 -> 8424 | F36: Looker Studio Pro $9/user/mes. Free tier suficiente para vistas básicas. Pro para BI embedido en portal investigadores y exportación a apps intranet.
A37: DataFlow (ETL ingesta datos clínicos) | B37: Ingesta automatizada: cBioPortal API, GDC API, INMEGEN, IMSS/ISSSTE · Streaming + batch · Procesamiento JSON → BigQuery | C37: 130 | D37: 12 | E37: =C37*D37 -> 1560 | F37: Dataflow: $0.056/vCPU-hr + $0.003756/GB-hr. Pipelines Nextflow complementan Dataflow.
A38: Subtotal — BigQuery + Looker Studio | C38: =SUM(C35:C37) -> 2021 | D38: 12 | E38: =SUM(E35:E37) -> 24252
A39: ▌ 6. GCP — SEGURIDAD, IAM & COMPLIANCE (MFA, HIPAA, LGPD México)
A40: Cloud Identity + MFA (Autenticación Multifactor) | B40: Cloud Identity Premium · 150 usuarios investigadores + 15 admins · MFA: Google Authenticator / hardware keys · SSO SAML institucional | C40: 990 | D40: 12 | E40: =C40*D40 -> 11880 | F40: Cloud Identity Premium: $6/usuario/mes. 165 usuarios totales (150 inv + 15 admin). MFA obligatorio para acceso a datos genómicos. LGPD México + HIPAA BAA.
A41: Secret Manager + KMS (cifrado llaves API) | B41: Gestión segura de API keys: ChEMBL, UniProt, cBioPortal, GDC, INMEGEN · KMS para cifrado datos en reposo (datos pacientes) | C41: 115 | D41: 12 | E41: =C41*D41 -> 1380 | F41: Secret Manager: $0.06/secret/mes + $0.03/10K accesos. KMS: $0.06/llave/mes. Cifrado AES-256 datos NGS. Requerido para BAA con GCP y cumplimiento NOM-024.
A42: Cloud DLP (Data Loss Prevention — datos pacientes) | B42: Inspección automática PII en outputs: nombres, IDs, datos clínicos · Previene exposición accidental de datos de pacientes | C42: 65 | D42: 12 | E42: =C42*D42 -> 780 | F42: Cloud DLP: $0.001/GB inspeccionado. Crítico para LGPD México y privacidad datos oncológicos.
A43: Access Context Manager + VPC Service Controls | B43: Perímetro de seguridad para datos genómicos · Solo acceso desde IPs autorizadas · Audit logs completos para trazabilidad científica | C43: 52 | D43: 12 | E43: =C43*D43 -> 624 | F43: VPC SC previene exfiltración datos. Requerido para datos TCGA y datos clínicos IMSS/ISSSTE.
A44: Subtotal — Seguridad & Compliance | C44: =SUM(C40:C43) -> 1222 | D44: 12 | E44: =SUM(E40:E43) -> 14664
A45: ▌ 7. DATABRICKS on GCP — Medallion Delta (Bronze/Silver/Gold) + MLOps + SQL Warehouse
A46: Databricks — Jobs Compute (pipelines ETL Medallion) | B46: Delta Lake Bronze→Silver→Gold · ETL mutaciones, variantes anotadas, docking scores · ~812 DBU/mes · $0.15/DBU (Jobs Compute) | C46: 122 | D46: 12 | E46: =C46*D46 -> 1464 | F46: Medallion Bronze: ingesta raw JSON/VCF. Silver: normalización, filtros Tier 1/2/3. Gold: cohorte analítica, variantes × fármaco, métricas por centro. Delta tables con ACID transactions para reproducibilidad.
A47: Databricks — SQL Warehouse (consultas investigadores) | B47: SQL Serverless Warehouse · 10 DBU/hr mínimo · Consultas ad-hoc sobre cohortes · Conexión Power BI / Looker para dashboards científicos | C47: 252 | D47: 12 | E47: =C47*D47 -> 3024 | F47: SQL Warehouse Serverless: $0.22/DBU. 8hr/día uso activo × 22 días. Auto-suspend 10 min. Acceso 150 investigadores para consultas SQL genómicas.
A48: Databricks — All-Purpose Cluster (exploración científica) | B48: Jupyter notebooks interactivos · Análisis exploratorio cohortes · Visualizaciones Plotly · 4 clusters × investigadores principales | C48: 366 | D48: 12 | E48: =C48*D48 -> 4392 | F48: All-Purpose: $0.40/DBU. 4 DBU/hr por cluster. 4hr/día análisis interactivo. Glow library para análisis variantes genómicas en Spark.
A49: Databricks — MLflow (tracking experimentos ML) | B49: Tracking automático: hiperparámetros modelos variantes, métricas RMSD, scores docking Vina, comparativas WT vs Mutada por cohorte | C49: 130 | D49: 12 | E49: =C49*D49 -> 1560 | F49: MLflow Managed: incluido en licencia Databricks. Modelo registry para versionar clasificadores VUS → Patogénica.
A50: Databricks — Delta Sharing (colaboración LATAM) | B50: Compartir Delta tables con investigadores latinoamericanos sin mover datos · 15 investigadores externos (read-only access) · Auditoría completa | C50: 98 | D50: 12 | E50: =C50*D50 -> 1176 | F50: Delta Sharing open protocol. Investigadores Argentina, Chile, Colombia pueden consultar cohorte mexicana sin descarga. Governance con Unity Catalog.
A51: Databricks — Unity Catalog (gobernanza datos) | B51: Catálogo central: tablas genómicas, modelos ML, notebooks científicos · Control acceso por institución · Lineage de datos | C51: 195 | D51: 12 | E51: =C51*D51 -> 2340 | F51: Unity Catalog: incluido en licencias Premium. Esencial para cumplimiento científico (reproducibilidad) y regulatorio (LGPD/NOM-024).
A52: Subtotal — Databricks on GCP — Medallion + MLOps | C52: =SUM(C46:C51) -> 1163 | D52: 12 | E52: =SUM(E46:E51) -> 13956
A53: ▌ 8. GEMINI LLM + RAG — Asistente Científico para Equipos de Investigación
A54: Gemini 1.5 Pro API — RAG Científico | B54: RAG sobre literatura oncológica, ClinVar, OncoKB, ChEMBL · Consultas: '¿Qué fármacos existen para PIK3CA H1047R?' · Estimado 2,400 queries/mes × investigadores | C54: 20 | D54: 12 | E54: =C54*D54 -> 240 | F54: Gemini 1.5 Pro: $0.0125/1K tokens input, $0.0375/1K output. Query típico ~2K tokens. RAG base: PubMed oncología, FDA labels, ClinVar.
A55: Vertex AI Vector Search (embeddings RAG) | B55: Índice vectorial literatura científica oncológica · 50K documentos: papers PubMed, ficha técnica fármacos, reportes ClinVar · Actualización mensual automática | C55: 260 | D55: 12 | E55: =C55*D55 -> 3120 | F55: Vertex AI Vector Search: $0.036/hr por nodo. 1 nodo suficiente para 50K docs. Embeddings: text-embedding-004 $0.025/M tokens.
A56: Gemini — Generación Reportes Clínicos Automatizada | B56: Auto-generación reportes por variante: resumen ejecutivo, métricas estructurales, candidatos farmacológicos, recomendación clínica · PDF/HTML | C56: 4 | D56: 12 | E56: =C56*D56 -> 48 | F56: Reporte por variante ~5K tokens output. Gemini 1.5 Flash $0.0001875/1K tokens output para reportes batch económicos.
A57: Subtotal — Gemini LLM + RAG | C57: =SUM(C54:C56) -> 284 | D57: 12 | E57: =SUM(E54:E56) -> 3408
A58: ▌ 9. ANTIGRAVITY IDE — Licencias Equipo Desarrollo & Soporte
A59: Antigravity IDE — Licencias Desarrolladores | B59: 10 licencias desarrolladores/bioinformáticos · Planning Mode + Gemini 3 Pro · Desarrollo pipeline GEN-MAMA-MX, microservicios, MLOps | C59: 300 | D59: 12 | E59: =C59*D59 -> 3600 | F59: Antigravity IDE (Google): ~$30/usuario/mes estimado. Usado en prototipo actual (Claude Sonnet + Gemini 3 Pro). Acelera desarrollo 4x vs IDE tradicional según documentación proyecto.
A60: Capacitación IA Agéntica + LLM RAGs en Gemini | B60: Workshop 40 horas: agentes IA, RAG científico, prompt engineering para oncología · 50 usuarios (investigadores + soporte técnico) | C60: 625 | D60: 12 | E60: =C60*D60 -> 7500 | F60: $150/usuario por workshop completo. Google Cloud Skills Boost + instructor especializado. Incluye: Gemini API, Vertex AI, RAG construction, agentes para análisis genómico.
A61: Subtotal — Antigravity IDE + Capacitación IA | C61: =SUM(C59:C60) -> 925 | D61: 12 | E61: =SUM(E59:E60) -> 11100
A62: ▌ 10. CAPACITACIÓN — GCP, Databricks, Pipeline GEN-MAMA-MX (50 usuarios)
A63: GCP Fundamentals + Bioinformatics on GCP | B63: 50 usuarios · Google Cloud Skills Boost · 20 cursos especializados · Bioinformatics on GCP, Vertex AI, BigQuery genomics | C63: 1250 | D63: 12 | E63: =C63*D63 -> 15000 | F63: $300/usuario cloud training completo (año). Google for Startups reduce 30% para académicos. Certificación: Professional Data Engineer recomendada para equipo técnico.
A64: Databricks Fundamentals + Genomics Lakehouse | B64: 50 usuarios · Databricks Academy · Delta Lake, MLflow, Unity Catalog · Especialización: Glow genomics library, VariantSpark | C64: 833 | D64: 12 | E64: =C64*D64 -> 9996 | F64: $200/usuario Databricks Academy (año). Incluye: Databricks Certified Associate. Genomics Lakehouse track: Delta tables para VCF/FASTQ processing.
A65: Pipeline GEN-MAMA-MX — Capacitación Interna | B65: Taller personalizado 32 hrs: uso de la plataforma, interpretación resultados docking, flujo biopsia→reporte, validación clínica · Para oncólogos y bioinformáticos | C65: 333 | D65: 12 | E65: =C65*D65 -> 3996 | F65: $80/usuario taller interno con instructor UNISON. Incluye: demo con TCGA-BRCA, casos reales PIK3CA H1047R, interpretación alpelisib.
A66: Subtotal — Capacitación GCP + Databricks + Pipeline | C66: =SUM(C63:C65) -> 2416 | D66: 12 | E66: =SUM(E63:E65) -> 28992
A67: ▌ 11. SOPORTE TÉCNICO — Plataformas Cloud + Bioinformática
A68: GCP Premium Support | B68: Premium Support GCP · SLA 1hr respuesta P1 · TAM dedicado · Revisión arquitectura bioinformática trimestral | C68: 975 | D68: 12 | E68: =C68*D68 -> 11700 | F68: GCP Premium Support: máx(3% gasto mensual, $1,500). Incluye Technical Account Manager. Requerido para SLA productivo con datos clínicos.
A69: Databricks Enterprise Support | B69: Enterprise Support Databricks · 24/7 · SLA 4hr P1 · Expert sessions MLOps y genomics Lakehouse | C69: 520 | D69: 12 | E69: =C69*D69 -> 6240 | F69: Databricks Enterprise Support: incluido en licencia Enterprise. Costo separado si se usa Pay-as-you-go: ~$800/mes.
A70: Soporte Bioinformático Especializado (L2/L3) | B70: 2 bioinformáticos cloud (FTE 0.5) · Soporte pipelines Nextflow, GATK, Boltz-2, AutoDock Vina · Troubleshooting NGS análisis | C70: 3900 | D70: 12 | E70: =C70*D70 -> 46800 | F70: Bioinformático cloud LATAM: ~$3,000/mes (medio tiempo). Alternativa: contrato soporte con Hospital Albert Einstein / Varsomics Brasil.
A71: Soporte Usuarios Investigadores (helpdesk) | B71: L1 helpdesk para 150 investigadores · Portal resultados, apps móviles · Documentación, videos tutoriales, FAQ genómico | C71: 325 | D71: 12 | E71: =C71*D71 -> 3900 | F71: 0.5 FTE helpdesk + base conocimiento Confluence. SLA 24hr para investigadores, 4hr para oncólogos IMSS en producción.
A72: Subtotal — Soporte Técnico | C72: =SUM(C68:C71) -> 5720 | D72: 12 | E72: =SUM(E68:E71) -> 68640
A73: ▌ 12. SERVICIOS PROFESIONALES — Desarrollo, Integración, MLOps
A74: Desarrollo Pipeline Bioinformático (DevOps/Bioinformática) | B74: Equipo 3 devs × 3 años · Nextflow pipeline manager, integración cBioPortal+GDC+INMEGEN, portal investigadores LATAM | C74: 15000 | D74: 12 | E74: =C74*D74 -> 180000 | F74: $5,000/mes por desarrollador bioinformático senior LATAM. Incluye: pipelines Nextflow WDL, API integrations, frontend portal, CI/CD.
A75: MLOps Engineering (Vertex AI + Databricks) | B75: 1.5 FTE MLOps · Kubeflow Pipelines, MLflow tracking, model versioning, A/B testing modelos variantes, monitoreo drift | C75: 9000 | D75: 12 | E75: =C75*D75 -> 108000 | F75: $6,000/mes MLOps engineer senior. Entregables: pipelines entrenamiento automático, inferencia batch 30K casos/año.
A76: Integración IMSS/ISSSTE/INMEGEN | B76: Consultoría integración sistemas institucionales · API FHIR HL7 · NOM-024 cumplimiento · Piloto Hermosillo 6 meses | C76: 2000 | D76: 12 | E76: =C76*D76 -> 24000 | F76: $2,000/mes consultoría integración HL7/FHIR. Requerido para transferir datos NGS IMSS → plataforma GCP. NOM-024-SSA3.
A77: Desarrollo App Móvil + Intranet Investigadores | B77: App iOS/Android para acceso resultados en campo · Portal web intranet para oncólogos · React Native + microservicios GKE | C77: 1950 | D77: 12 | E77: =C77*D77 -> 23400 | F77: $3,000/mes mantenimiento app post-desarrollo inicial. Año 1: desarrollo activo. Año 2-3: mantenimiento + features.
A78: Subtotal — Servicios Profesionales | C78: =SUM(C74:C77) -> 27950 | D78: 12 | E78: =SUM(E74:E77) -> 335400
A79: ▌ 13. LICENCIAS SOFTWARE — MongoDB Atlas, Nextflow Tower, GitHub Enterprise, otros
A80: MongoDB Atlas (nube — fase análisis) | B80: M10 cluster · 2GB RAM · Almacén intermedio ingesta · Colecciones: mutations, top_variants, fasta_sequences | C80: 37 | D80: 12 | E80: =C80*D80 -> 444 | F80: MongoDB Atlas M10: $57/mes. Reemplaza MongoDB local para ambiente cloud. Solo fase análisis; Gold layer usa BigQuery + Delta Lake.
A81: Nextflow Tower (orquestación pipelines NGS) | B81: Nextflow Tower Pro · Orquestación visual pipelines NGS en GCP · 12 pipelines paralelos · Integración GitHub | C81: 325 | D81: 12 | E81: =C81*D81 -> 3900 | F81: Nextflow Tower Pro: ~$500/mes (10 workspaces). Workflows: GATK WES, Boltz-2 batch, docking paralelo, QC reports.
A82: GitHub Enterprise (control versiones + CI/CD) | B82: 50 licencias · Actions ilimitadas · Advanced Security · Dependabot para dependencias bioinformáticas | C82: 1050 | D82: 12 | E82: =C82*D82 -> 12600 | F82: GitHub Enterprise: $21/usuario/mes. Repositorios: pipeline GEN-MAMA-MX, microservicios, infraestructura IaC (Terraform).
A83: Tableau / PowerBI (alternativa Looker Studio) | B83: Dashboards avanzados para presentaciones institucionales · 20 licencias para PIs y administradores | C83: 910 | D83: 12 | E83: =C83*D83 -> 10920 | F83: Tableau Creator: $70/usuario/mes. Alternativa a Looker Studio Pro para reportes ejecutivos CONACYT, Google.org, publicaciones científicas.
A84: Jira + Confluence (gestión proyecto científico) | B84: Backlog bioinformático, sprints, documentación técnica · 20 usuarios equipo desarrollo + PIs | C84: 160 | D84: 12 | E84: =C84*D84 -> 1920 | F84: Atlassian Cloud Standard: $8.15/usuario/mes. Usado en prototipo (ver GENMAMAMX_Backlog_Prototipo.docx).
A85: Subtotal — Licencias Software Adicionales | C85: =SUM(C80:C84) -> 2482 | D85: 12 | E85: =SUM(E80:E84) -> 29784
A87: TOTAL Año2 — GEN-MAMA-MX | C87: =(E11+E18+E24+E33+E38+E44+E52+E57+E61+E66+E72+E78+E85)/12 -> 52559 | D87: 12 | E87: =E11+E18+E24+E33+E38+E44+E52+E57+E61+E66+E72+E78+E85 -> 630708 | F87: Factor ramp: 65% | Casos NGS/año: 19,500 | Centros: 12
C200: =E87 -> 630708

Sheet Año3
A1: GEN-MAMA-MX — Estimación de Costos Año3 | Factor de rampa: 100% | Casos NGS: 30,000 | Centros activos: 20
A2: USD por mes × 12 meses · Todos los costos en dólares americanos · Precios GCP us-central1 (Iowa) / Databricks on GCP 2025
A4: Componente / Recurso | B4: Especificación Técnica | C4: Costo/Mes USD | D4: Meses | E4: Total Anual USD | F4: Notas / Justificación
A5: ▌ 1. GCP — CÓMPUTO GPU / CPU (Boltz-2, AlphaFold3, NGS Pipelines)
A6: GPU Cluster — Boltz-2 / AlphaFold3 | B6: n1-standard-8 + NVIDIA T4 GPU · 219 GPU-hrs/mes · $1.40/hr · Predicción estructural 3D para 2,500 casos/mes × 15 genes objetivo | C6: 307 | D6: 12 | E6: =C6*D6 -> 3684 | F6: Ref: Fovus $0.10/sim; en GCP T4 ~20min/sim = $0.47/sim. Escala con casos NGS.
A7: GPU Premium — Lotes grandes (spot/preemptible) | B7: Preemptible T4: $0.35/hr · Ahorro 75% en lotes no urgentes · Docking masivo (Vina GPU): 27,500 pares receptor-ligando/mes | C7: 26 | D7: 12 | E7: =C7*D7 -> 312 | F7: Ref: Vina GPU $0.95/10K dockings. Mix preemptible/on-demand.
A8: CPU — Pipelines NGS (WES alignment + variant calling) | B8: n2-highcpu-32 · $0.94/hr · GATK/BWA/DeepVariant · 6,250 CPU-hrs/mes para 2,500 exomas/mes | C8: 5875 | D8: 12 | E8: =C8*D8 -> 70500 | F8: Ref: Franzoso 2025 — 64-96 CPUs por muestra WES en GCP. $300 WES cost incluye seq+análisis.
A9: CPU — Bioinformática General (MongoDB, ingesta, FASTA, QC) | B9: e2-standard-8 · $0.27/hr · Always-on para APIs, ingesta automatizada, QC pipelines | C9: 389 | D9: 12 | E9: =C9*D9 -> 4668 | F9: 2 instancias always-on: servidor APIs cBioPortal/UniProt, servidor MongoDB intermediario.
A10: Cloud Run — Microservicios (consulta resultados) | B10: Cloud Run autoscale · 2M requests/mes · 512MB RAM · API de resultados genomicos para investigadores LATAM | C10: 80 | D10: 12 | E10: =C10*D10 -> 960 | F10: Cloud Run: $0.40/M requests. Factor ramp aplicado.
A11: Subtotal — GCP Cómputo GPU/CPU | C11: =SUM(C6:C10) -> 6677 | D11: 12 | E11: =SUM(E6:E10) -> 80124
A12: ▌ 2. GCP — CLOUD STORAGE (Bronze/Silver/Gold + estructuras 3D)
A13: GCS Bronze — Datos RAW NGS (FASTQ, BAM, VCF) | B13: Standard Storage · 146.5 TB acumulado · $0.020/GB/mes · FASTQ 2×150bp WES (~5GB/muestra) + BAM + VCF raw | C13: 3000 | D13: 12 | E13: =C13*D13 -> 36000 | F13: WES FASTQ ~5GB/muestra. Ciclo vida: 90 días standard → Nearline ($0.010). Retención 3 años.
A14: GCS Silver — Datos Procesados (mutaciones filtradas, FASTA) | B14: Nearline Storage · 21.97 TB · $0.010/GB/mes · JSON anotados, FASTA WT/mutados por variante, métricas pLDDT | C14: 225 | D14: 12 | E14: =C14*D14 -> 2700 | F14: ~15% del volumen Bronze. Incluye top_variants.json, structural_metrics.json por cohorte.
A15: GCS Gold — Resultados Finales + Estructuras 3D | B15: Standard Storage · 2.20 TB estructuras CIF/PDB + 2.20 TB · $0.020/GB/mes · mmCIF Boltz-2, poses docking PDBQT, reportes HTML/PDF | C15: 90 | D15: 12 | E15: =C15*D15 -> 1080 | F15: Estructuras 3D: ~5MB/variante CIF + poses docking. Acceso frecuente por investigadores.
A16: GCS Archival — Backup largo plazo | B16: Archive Storage · $0.0012/GB/mes · Snapshots mensuales completos | C16: 90 | D16: 12 | E16: =C16*D16 -> 1080 | F16: 50% del Bronze archivado. Recuperación $0.05/GB. Para auditoría y reproducibilidad científica.
A17: Egress / Transfer | B17: Egress internet: $0.08/GB · Investigadores LATAM descargando reportes/estructuras · Estimado 250 GB/mes salida | C17: 20 | D17: 12 | E17: =C17*D17 -> 240 | F17: Reportes PDF ~2MB + estructuras CIF ~5MB × casos activos. CDN reduce costo.
A18: Subtotal — GCP Cloud Storage | C18: =SUM(C13:C17) -> 3425 | D18: 12 | E18: =SUM(E13:E17) -> 41100
A19: ▌ 3. GCP — NETWORKING, API GATEWAY & SEGURIDAD
A20: Cloud Load Balancing + Cloud CDN | B20: Global HTTPS LB · $0.008/GB procesado · CDN para estructuras 3D y dashboards · 150 usuarios activos + aplicaciones móviles CONAFOR | C20: 400 | D20: 12 | E20: =C20*D20 -> 4800 | F20: LB: $18/mes base + $0.008/GB. CDN ahorra egress para assets estáticos (estructuras CIF).
A21: API Gateway / Cloud Endpoints | B21: API REST para integración IMSS/ISSSTE, apps móviles, intranet investigadores · 10M calls/mes estimado en escala plena | C21: 300 | D21: 12 | E21: =C21*D21 -> 3600 | F21: $3.50/M API calls primeros 2M, luego $1.50/M. Incluye quota management y API keys por institución.
A22: Cloud Armor (WAF + DDoS) | B22: Protección WAF para APIs genómicas · HIPAA compliance · $5/política + $0.75/M requests protegidas | C22: 200 | D22: 12 | E22: =C22*D22 -> 2400 | F22: Dato médico sensible requiere protección WAF. HIPAA BAA con GCP.
A23: VPC + Interconnect (privado centros investigación) | B23: Cloud VPN HA para conexión IMSS/ISSSTE/INMEGEN · $0.05/hr por túnel | C23: 72 | D23: 12 | E23: =C23*D23 -> 864 | F23: 2 túneles HA VPN: UNISON Hermosillo + INMEGEN CDMX. Transferencia segura muestras NGS.
A24: Subtotal — GCP Networking & API | C24: =SUM(C20:C23) -> 972 | D24: 12 | E24: =SUM(E20:E23) -> 11664
A25: ▌ 4. GCP — OpenShift / GKE · DevOps · MLOps · Monitoreo Grafana
A26: GKE (Google Kubernetes Engine) — Cluster Microservicios | B26: 3 nodos e2-standard-4 (always-on) + autoscale 1-8 nodos · Microservicios: consulta resultados, API genómica, portal investigadores LATAM | C26: 361 | D26: 12 | E26: =C26*D26 -> 4332 | F26: e2-standard-4: $0.134/hr. GKE management fee: $72/mes. Istio service mesh incluido.
A27: OpenShift on GCP (ROSA equivalent) — Apps Institucionales | B27: OpenShift 4.x en GCP · Control plane managed · Workers n2-standard-4 · Apps intranet IMSS/ISSSTE + portal genómico + app móvil backend | C27: 800 | D27: 12 | E27: =C27*D27 -> 9600 | F27: OpenShift Enterprise: ~$0.11/vCPU/hr. 4 workers × 4 vCPU = ~$1,267/mes base. Factor ramp.
A28: Cloud Build + Artifact Registry (CI/CD) | B28: CI/CD para pipelines bioinformáticos + microservicios · 120 builds/mes · Docker images · GitHub Enterprise integration | C28: 150 | D28: 12 | E28: =C28*D28 -> 1800 | F28: Cloud Build: primeros 120min/día gratis. Artifact Registry: $0.10/GB. GitHub Enterprise separado.
A29: Vertex AI Pipelines (MLOps — Kubeflow Pipelines) | B29: Orquestación pipelines NGS, entrenamiento modelos variantes, inferencia batch · 20 pipelines paralelos por centro | C29: 1000 | D29: 12 | E29: =C29*D29 -> 12000 | F29: Vertex AI Pipelines: $0.03/vCPU-hr + $0.005/GB-hr. Reemplaza Airflow self-managed.
A30: Vertex AI Model Registry + Endpoint (modelo variantes) | B30: Registro versiones modelos ML (clasificación VUS, predicción afinidad) · Endpoints para inferencia online <500ms · Explicabilidad integrada | C30: 300 | D30: 12 | E30: =C30*D30 -> 3600 | F30: Vertex AI Prediction: $0.051/hr nodo n1-standard-4. 1 endpoint always-on + batch prediction.
A31: Grafana Cloud (monitoreo integral) | B31: Grafana Cloud Pro · Métricas GCP + Databricks + pipelines Nextflow · Dashboards: GPU utilization, pipeline success rate, costo/muestra, alertas | C31: 200 | D31: 12 | E31: =C31*D31 -> 2400 | F31: Grafana Cloud Pro: $299/mes (50K métricas). Integra con Cloud Monitoring via plugin. Dashboards: NGS throughput, docking queue, GPU %, Databricks job latency.
A32: Cloud Monitoring + Logging + Trace | B32: Operations Suite (stackdriver) · Logs retención 30 días · Custom metrics pipelines bioinformáticos · Budget alerts | C32: 150 | D32: 12 | E32: =C32*D32 -> 1800 | F32: First 50GB logs/mes gratis. Custom metrics: $0.10/metric/mes. Trace: $0.20/M spans.
A33: Subtotal — OpenShift/GKE + DevOps + MLOps + Grafana | C33: =SUM(C26:C32) -> 2961 | D33: 12 | E33: =SUM(E26:E32) -> 35532
A34: ▌ 5. GCP — BigQuery (SQL Warehouse Genómico) + Looker Studio Dashboards
A35: BigQuery — SQL Warehouse Genómico | B35: Almacén central: mutaciones somáticas, variantes anotadas, métricas docking · 60.0 TB activo · $5/TB consultas · Storage $0.020/GB/mes | C35: 1829 | D35: 12 | E35: =C35*D35 -> 21948 | F35: BQ free: 10GB storage + 1TB queries/mes. Superado a partir Año 2. Flat-rate $2,000/mes considerado Año 3 si queries >10TB/mes.
A36: Looker Studio Pro — Dashboards Investigadores | B36: Dashboards interactivos: distribución variantes, heatmap docking, progreso cohorte por centro · 150 usuarios · $9/usuario/mes (Pro) | C36: 1350 | D36: 12 | E36: =C36*D36 -> 16200 | F36: Looker Studio Pro $9/user/mes. Free tier suficiente para vistas básicas. Pro para BI embedido en portal investigadores y exportación a apps intranet.
A37: DataFlow (ETL ingesta datos clínicos) | B37: Ingesta automatizada: cBioPortal API, GDC API, INMEGEN, IMSS/ISSSTE · Streaming + batch · Procesamiento JSON → BigQuery | C37: 200 | D37: 12 | E37: =C37*D37 -> 2400 | F37: Dataflow: $0.056/vCPU-hr + $0.003756/GB-hr. Pipelines Nextflow complementan Dataflow.
A38: Subtotal — BigQuery + Looker Studio | C38: =SUM(C35:C37) -> 3379 | D38: 12 | E38: =SUM(E35:E37) -> 40548
A39: ▌ 6. GCP — SEGURIDAD, IAM & COMPLIANCE (MFA, HIPAA, LGPD México)
A40: Cloud Identity + MFA (Autenticación Multifactor) | B40: Cloud Identity Premium · 150 usuarios investigadores + 15 admins · MFA: Google Authenticator / hardware keys · SSO SAML institucional | C40: 990 | D40: 12 | E40: =C40*D40 -> 11880 | F40: Cloud Identity Premium: $6/usuario/mes. 165 usuarios totales (150 inv + 15 admin). MFA obligatorio para acceso a datos genómicos. LGPD México + HIPAA BAA.
A41: Secret Manager + KMS (cifrado llaves API) | B41: Gestión segura de API keys: ChEMBL, UniProt, cBioPortal, GDC, INMEGEN · KMS para cifrado datos en reposo (datos pacientes) | C41: 150 | D41: 12 | E41: =C41*D41 -> 1800 | F41: Secret Manager: $0.06/secret/mes + $0.03/10K accesos. KMS: $0.06/llave/mes. Cifrado AES-256 datos NGS. Requerido para BAA con GCP y cumplimiento NOM-024.
A42: Cloud DLP (Data Loss Prevention — datos pacientes) | B42: Inspección automática PII en outputs: nombres, IDs, datos clínicos · Previene exposición accidental de datos de pacientes | C42: 100 | D42: 12 | E42: =C42*D42 -> 1200 | F42: Cloud DLP: $0.001/GB inspeccionado. Crítico para LGPD México y privacidad datos oncológicos.
A43: Access Context Manager + VPC Service Controls | B43: Perímetro de seguridad para datos genómicos · Solo acceso desde IPs autorizadas · Audit logs completos para trazabilidad científica | C43: 80 | D43: 12 | E43: =C43*D43 -> 960 | F43: VPC SC previene exfiltración datos. Requerido para datos TCGA y datos clínicos IMSS/ISSSTE.
A44: Subtotal — Seguridad & Compliance | C44: =SUM(C40:C43) -> 1320 | D44: 12 | E44: =SUM(E40:E43) -> 15840
A45: ▌ 7. DATABRICKS on GCP — Medallion Delta (Bronze/Silver/Gold) + MLOps + SQL Warehouse
A46: Databricks — Jobs Compute (pipelines ETL Medallion) | B46: Delta Lake Bronze→Silver→Gold · ETL mutaciones, variantes anotadas, docking scores · ~1,250 DBU/mes · $0.15/DBU (Jobs Compute) | C46: 188 | D46: 12 | E46: =C46*D46 -> 2256 | F46: Medallion Bronze: ingesta raw JSON/VCF. Silver: normalización, filtros Tier 1/2/3. Gold: cohorte analítica, variantes × fármaco, métricas por centro. Delta tables con ACID transactions para reproducibilidad.
A47: Databricks — SQL Warehouse (consultas investigadores) | B47: SQL Serverless Warehouse · 10 DBU/hr mínimo · Consultas ad-hoc sobre cohortes · Conexión Power BI / Looker para dashboards científicos | C47: 387 | D47: 12 | E47: =C47*D47 -> 4644 | F47: SQL Warehouse Serverless: $0.22/DBU. 8hr/día uso activo × 22 días. Auto-suspend 10 min. Acceso 150 investigadores para consultas SQL genómicas.
A48: Databricks — All-Purpose Cluster (exploración científica) | B48: Jupyter notebooks interactivos · Análisis exploratorio cohortes · Visualizaciones Plotly · 4 clusters × investigadores principales | C48: 563 | D48: 12 | E48: =C48*D48 -> 6756 | F48: All-Purpose: $0.40/DBU. 4 DBU/hr por cluster. 4hr/día análisis interactivo. Glow library para análisis variantes genómicas en Spark.
A49: Databricks — MLflow (tracking experimentos ML) | B49: Tracking automático: hiperparámetros modelos variantes, métricas RMSD, scores docking Vina, comparativas WT vs Mutada por cohorte | C49: 200 | D49: 12 | E49: =C49*D49 -> 2400 | F49: MLflow Managed: incluido en licencia Databricks. Modelo registry para versionar clasificadores VUS → Patogénica.
A50: Databricks — Delta Sharing (colaboración LATAM) | B50: Compartir Delta tables con investigadores latinoamericanos sin mover datos · 15 investigadores externos (read-only access) · Auditoría completa | C50: 150 | D50: 12 | E50: =C50*D50 -> 1800 | F50: Delta Sharing open protocol. Investigadores Argentina, Chile, Colombia pueden consultar cohorte mexicana sin descarga. Governance con Unity Catalog.
A51: Databricks — Unity Catalog (gobernanza datos) | B51: Catálogo central: tablas genómicas, modelos ML, notebooks científicos · Control acceso por institución · Lineage de datos | C51: 300 | D51: 12 | E51: =C51*D51 -> 3600 | F51: Unity Catalog: incluido en licencias Premium. Esencial para cumplimiento científico (reproducibilidad) y regulatorio (LGPD/NOM-024).
A52: Subtotal — Databricks on GCP — Medallion + MLOps | C52: =SUM(C46:C51) -> 1788 | D52: 12 | E52: =SUM(E46:E51) -> 21456
A53: ▌ 8. GEMINI LLM + RAG — Asistente Científico para Equipos de Investigación
A54: Gemini 1.5 Pro API — RAG Científico | B54: RAG sobre literatura oncológica, ClinVar, OncoKB, ChEMBL · Consultas: '¿Qué fármacos existen para PIK3CA H1047R?' · Estimado 4,000 queries/mes × investigadores | C54: 50 | D54: 12 | E54: =C54*D54 -> 600 | F54: Gemini 1.5 Pro: $0.0125/1K tokens input, $0.0375/1K output. Query típico ~2K tokens. RAG base: PubMed oncología, FDA labels, ClinVar.
A55: Vertex AI Vector Search (embeddings RAG) | B55: Índice vectorial literatura científica oncológica · 50K documentos: papers PubMed, ficha técnica fármacos, reportes ClinVar · Actualización mensual automática | C55: 400 | D55: 12 | E55: =C55*D55 -> 4800 | F55: Vertex AI Vector Search: $0.036/hr por nodo. 1 nodo suficiente para 50K docs. Embeddings: text-embedding-004 $0.025/M tokens.
A56: Gemini — Generación Reportes Clínicos Automatizada | B56: Auto-generación reportes por variante: resumen ejecutivo, métricas estructurales, candidatos farmacológicos, recomendación clínica · PDF/HTML | C56: 10 | D56: 12 | E56: =C56*D56 -> 120 | F56: Reporte por variante ~5K tokens output. Gemini 1.5 Flash $0.0001875/1K tokens output para reportes batch económicos.
A57: Subtotal — Gemini LLM + RAG | C57: =SUM(C54:C56) -> 460 | D57: 12 | E57: =SUM(E54:E56) -> 5520
A58: ▌ 9. ANTIGRAVITY IDE — Licencias Equipo Desarrollo & Soporte
A59: Antigravity IDE — Licencias Desarrolladores | B59: 10 licencias desarrolladores/bioinformáticos · Planning Mode + Gemini 3 Pro · Desarrollo pipeline GEN-MAMA-MX, microservicios, MLOps | C59: 300 | D59: 12 | E59: =C59*D59 -> 3600 | F59: Antigravity IDE (Google): ~$30/usuario/mes estimado. Usado en prototipo actual (Claude Sonnet + Gemini 3 Pro). Acelera desarrollo 4x vs IDE tradicional según documentación proyecto.
A60: Capacitación IA Agéntica + LLM RAGs en Gemini | B60: Workshop 40 horas: agentes IA, RAG científico, prompt engineering para oncología · 50 usuarios (investigadores + soporte técnico) | C60: 625 | D60: 12 | E60: =C60*D60 -> 7500 | F60: $150/usuario por workshop completo. Google Cloud Skills Boost + instructor especializado. Incluye: Gemini API, Vertex AI, RAG construction, agentes para análisis genómico.
A61: Subtotal — Antigravity IDE + Capacitación IA | C61: =SUM(C59:C60) -> 925 | D61: 12 | E61: =SUM(E59:E60) -> 11100
A62: ▌ 10. CAPACITACIÓN — GCP, Databricks, Pipeline GEN-MAMA-MX (50 usuarios)
A63: GCP Fundamentals + Bioinformatics on GCP | B63: 50 usuarios · Google Cloud Skills Boost · 20 cursos especializados · Bioinformatics on GCP, Vertex AI, BigQuery genomics | C63: 1250 | D63: 12 | E63: =C63*D63 -> 15000 | F63: $300/usuario cloud training completo (año). Google for Startups reduce 30% para académicos. Certificación: Professional Data Engineer recomendada para equipo técnico.
A64: Databricks Fundamentals + Genomics Lakehouse | B64: 50 usuarios · Databricks Academy · Delta Lake, MLflow, Unity Catalog · Especialización: Glow genomics library, VariantSpark | C64: 833 | D64: 12 | E64: =C64*D64 -> 9996 | F64: $200/usuario Databricks Academy (año). Incluye: Databricks Certified Associate. Genomics Lakehouse track: Delta tables para VCF/FASTQ processing.
A65: Pipeline GEN-MAMA-MX — Capacitación Interna | B65: Taller personalizado 32 hrs: uso de la plataforma, interpretación resultados docking, flujo biopsia→reporte, validación clínica · Para oncólogos y bioinformáticos | C65: 333 | D65: 12 | E65: =C65*D65 -> 3996 | F65: $80/usuario taller interno con instructor UNISON. Incluye: demo con TCGA-BRCA, casos reales PIK3CA H1047R, interpretación alpelisib.
A66: Subtotal — Capacitación GCP + Databricks + Pipeline | C66: =SUM(C63:C65) -> 2416 | D66: 12 | E66: =SUM(E63:E65) -> 28992
A67: ▌ 11. SOPORTE TÉCNICO — Plataformas Cloud + Bioinformática
A68: GCP Premium Support | B68: Premium Support GCP · SLA 1hr respuesta P1 · TAM dedicado · Revisión arquitectura bioinformática trimestral | C68: 1500 | D68: 12 | E68: =C68*D68 -> 18000 | F68: GCP Premium Support: máx(3% gasto mensual, $1,500). Incluye Technical Account Manager. Requerido para SLA productivo con datos clínicos.
A69: Databricks Enterprise Support | B69: Enterprise Support Databricks · 24/7 · SLA 4hr P1 · Expert sessions MLOps y genomics Lakehouse | C69: 800 | D69: 12 | E69: =C69*D69 -> 9600 | F69: Databricks Enterprise Support: incluido en licencia Enterprise. Costo separado si se usa Pay-as-you-go: ~$800/mes.
A70: Soporte Bioinformático Especializado (L2/L3) | B70: 2 bioinformáticos cloud (FTE 0.5) · Soporte pipelines Nextflow, GATK, Boltz-2, AutoDock Vina · Troubleshooting NGS análisis | C70: 6000 | D70: 12 | E70: =C70*D70 -> 72000 | F70: Bioinformático cloud LATAM: ~$3,000/mes (medio tiempo). Alternativa: contrato soporte con Hospital Albert Einstein / Varsomics Brasil.
A71: Soporte Usuarios Investigadores (helpdesk) | B71: L1 helpdesk para 150 investigadores · Portal resultados, apps móviles · Documentación, videos tutoriales, FAQ genómico | C71: 500 | D71: 12 | E71: =C71*D71 -> 6000 | F71: 0.5 FTE helpdesk + base conocimiento Confluence. SLA 24hr para investigadores, 4hr para oncólogos IMSS en producción.
A72: Subtotal — Soporte Técnico | C72: =SUM(C68:C71) -> 8800 | D72: 12 | E72: =SUM(E68:E71) -> 105600
A73: ▌ 12. SERVICIOS PROFESIONALES — Desarrollo, Integración, MLOps
A74: Desarrollo Pipeline Bioinformático (DevOps/Bioinformática) | B74: Equipo 3 devs × 3 años · Nextflow pipeline manager, integración cBioPortal+GDC+INMEGEN, portal investigadores LATAM | C74: 15000 | D74: 12 | E74: =C74*D74 -> 180000 | F74: $5,000/mes por desarrollador bioinformático senior LATAM. Incluye: pipelines Nextflow WDL, API integrations, frontend portal, CI/CD.
A75: MLOps Engineering (Vertex AI + Databricks) | B75: 1.5 FTE MLOps · Kubeflow Pipelines, MLflow tracking, model versioning, A/B testing modelos variantes, monitoreo drift | C75: 9000 | D75: 12 | E75: =C75*D75 -> 108000 | F75: $6,000/mes MLOps engineer senior. Entregables: pipelines entrenamiento automático, inferencia batch 30K casos/año.
A76: Integración IMSS/ISSSTE/INMEGEN | B76: Consultoría integración sistemas institucionales · API FHIR HL7 · NOM-024 cumplimiento · Piloto Hermosillo 6 meses | C76: 2000 | D76: 12 | E76: =C76*D76 -> 24000 | F76: $2,000/mes consultoría integración HL7/FHIR. Requerido para transferir datos NGS IMSS → plataforma GCP. NOM-024-SSA3.
A77: Desarrollo App Móvil + Intranet Investigadores | B77: App iOS/Android para acceso resultados en campo · Portal web intranet para oncólogos · React Native + microservicios GKE | C77: 3000 | D77: 12 | E77: =C77*D77 -> 36000 | F77: $3,000/mes mantenimiento app post-desarrollo inicial. Año 1: desarrollo activo. Año 2-3: mantenimiento + features.
A78: Subtotal — Servicios Profesionales | C78: =SUM(C74:C77) -> 29000 | D78: 12 | E78: =SUM(E74:E77) -> 348000
A79: ▌ 13. LICENCIAS SOFTWARE — MongoDB Atlas, Nextflow Tower, GitHub Enterprise, otros
A80: MongoDB Atlas (nube — fase análisis) | B80: M10 cluster · 2GB RAM · Almacén intermedio ingesta · Colecciones: mutations, top_variants, fasta_sequences | C80: 57 | D80: 12 | E80: =C80*D80 -> 684 | F80: MongoDB Atlas M10: $57/mes. Reemplaza MongoDB local para ambiente cloud. Solo fase análisis; Gold layer usa BigQuery + Delta Lake.
A81: Nextflow Tower (orquestación pipelines NGS) | B81: Nextflow Tower Pro · Orquestación visual pipelines NGS en GCP · 20 pipelines paralelos · Integración GitHub | C81: 500 | D81: 12 | E81: =C81*D81 -> 6000 | F81: Nextflow Tower Pro: ~$500/mes (10 workspaces). Workflows: GATK WES, Boltz-2 batch, docking paralelo, QC reports.
A82: GitHub Enterprise (control versiones + CI/CD) | B82: 50 licencias · Actions ilimitadas · Advanced Security · Dependabot para dependencias bioinformáticas | C82: 1050 | D82: 12 | E82: =C82*D82 -> 12600 | F82: GitHub Enterprise: $21/usuario/mes. Repositorios: pipeline GEN-MAMA-MX, microservicios, infraestructura IaC (Terraform).
A83: Tableau / PowerBI (alternativa Looker Studio) | B83: Dashboards avanzados para presentaciones institucionales · 20 licencias para PIs y administradores | C83: 1400 | D83: 12 | E83: =C83*D83 -> 16800 | F83: Tableau Creator: $70/usuario/mes. Alternativa a Looker Studio Pro para reportes ejecutivos CONACYT, Google.org, publicaciones científicas.
A84: Jira + Confluence (gestión proyecto científico) | B84: Backlog bioinformático, sprints, documentación técnica · 20 usuarios equipo desarrollo + PIs | C84: 160 | D84: 12 | E84: =C84*D84 -> 1920 | F84: Atlassian Cloud Standard: $8.15/usuario/mes. Usado en prototipo (ver GENMAMAMX_Backlog_Prototipo.docx).
A85: Subtotal — Licencias Software Adicionales | C85: =SUM(C80:C84) -> 3167 | D85: 12 | E85: =SUM(E80:E84) -> 38004
A87: TOTAL Año3 — GEN-MAMA-MX | C87: =(E11+E18+E24+E33+E38+E44+E52+E57+E61+E66+E72+E78+E85)/12 -> 65290 | D87: 12 | E87: =E11+E18+E24+E33+E38+E44+E52+E57+E61+E66+E72+E78+E85 -> 783480 | F87: Factor ramp: 100% | Casos NGS/año: 30,000 | Centros: 20
C200: =E87 -> 783480

Sheet AlphaFold3 DeepMind
A1: 🔬 AlphaFold 3 (Google DeepMind) — Estrategia de Acceso Automatizado y Estimación de Costos
A2: GEN-MAMA-MX · Predicción estructural 3D proteínas Wild-Type y Mutadas · Pipeline batch automatizado para 30,000 casos/año · Actualizado Marzo 2026
A3: RESUMEN EJECUTIVO: AlphaFold 3 (AF3) de Google DeepMind / Isomorphic Labs es la herramienta de predicción estructural más precisa del mundo para proteínas, DNA, RNA y ligandos. Para GEN-MAMA-MX existe una jerarquía de 4 modos de acceso: (1) AlphaFold Server GRATIS limitado a 30 jobs/día — para prototipado; (2) AF3 self-hosted en GCP A100 ~$0.47/predicción — para producción; (3) AlphaFast serverless vía Modal ~$0.035/predicción — para alto throughput; (4) AlphaFold DB GRATIS — para proteínas WT ya predichas (≥200M estructuras disponibles). El modelo recomendado para GEN-MAMA-MX combina AlphaFold DB (descarga gratuita WT) + AF3 self-hosted (solo mutadas).
A5: 📋 MODOS DE ACCESO A AlphaFold 3 — Comparativa
A6: Modo de Acceso | B6: Descripción y Limitaciones | C6: Costo | D6: Throughput | E6: Requiere GPU | F6: Recomendación GEN-MAMA-MX
A7: ① AlphaFold Server (Web UI / JSON upload) | B7: Gratis. alphafoldserver.com. 30 jobs/día/cuenta. Soporta proteínas, DNA, RNA, ligandos. JSON batch upload: hasta 100 drafts por archivo, máx 500 drafts en historial. Sólo uso no-comercial (CC-BY-NC-SA 4.0). Sin API oficial pública. | C7: $0 (GRATIS) | D7: 30 jobs/día por cuenta | E7: No (cloud DeepMind) | F7: ✅ PROTOTIPO / Validación ⚠️ Solo 30 genes WT por día
A8: ② AlphaFold 3 Self-Hosted en GCP (A100/H100) | B8: Código open-source (CC-BY-NC-SA 4.0). Pesos solicitados vía Google Form. Instalación Docker en VM GCP a2-ultragpu-1g (A100 80GB). Bases de datos: ~1 TB SSD. RAM mínimo 64GB. Batch vía JSON. Requiere aprobación de DeepMind (2-3 días hábiles). Solo uso académico/no-comercial. Modelo oficial: a2-ultragpu-1g = 12 CPUs, 170GB RAM, 1 TB SSD + A100 80GB. | C8: ~$3.67/hr (a2-highgpu) ~$0.47/predicción (~8 min/pred, 7-8 preds/hr) | D8: 7-8 preds/hr/GPU → 56-64 preds/día por VM | E8: ✅ A100 80GB obligatorio (Compute Cap 8.0+) | F8: ✅ PRODUCCIÓN Mejor para mutadas Control total
A9: ③ AlphaFast (AlphaFold 3 GPU-accelerated, serverless) | B9: Framework open-source (RomeroLab/alphafast, Feb 2026). Reemplaza CPU-bound MSA por MMseqs2-GPU. 22.8× más rápido que AF3 estándar. Deployment serverless vía Modal (proveedor cloud). Requiere pesos AF3 de Google + cuenta Modal. 8 segundos/input con 4×H200 GPUs. $0.035/predicción en H200. | C9: $0.035/predicción (Modal serverless) 22.8× más rápido que AF3 | D9: 8 seg/pred con 4×H200 → ~10,800 preds/día por nodo Ideal para batches grandes | E9: ✅ H200 GPU (Modal) No requiere VM propia | F9: ✅ ALTO THROUGHPUT Año 2-3 cuando volumen >1,000 preds/mes
A10: ④ AlphaFold Protein Structure Database (EBI) | B10: Base de datos GRATIS: >200 millones de estructuras pre-calculadas. Incluye proteoma humano completo. Acceso REST API del EMBL-EBI. Descarga individual por UniProt ID o proteomas completos. Licencia CC-BY-4.0 (uso académico Y comercial). Sin límite de descarga. Solo cubre proteínas Wild-Type (WT). Mutadas NO están en la DB. | C10: $0 (GRATIS) Sin límite descarga CC-BY-4.0 | D10: Sin límite — API REST Descarga masiva OK No requiere GPU | E10: ❌ No requiere GPU | F10: ✅ USAR PRIMERO para WT Caché local en GCS Evita re-computar WT
A11: ⑤ ColabFold (AlphaFold2 / AF3-like) | B11: Alternativa open-source. AlphaFold2 + MMseqs2. Google Colab T4 gratuito (limitado). Colab Pro $10/mes. Sin restricción de uso comercial. Para proteínas <390aa. Útil como fallback si AF3 self-hosted no está disponible. | C11: $0-$10/mes (Colab Pro) ~$0.47/pred en GCP T4 | D11: ~3 preds/hr en T4 Google Colab | E11: ✅ T4 GPU (Colab) o GCP VM | F11: ⚠️ BACKUP / Fallback Menos preciso que AF3 Ya usado en prototipo
A13: 🎯 ESTRATEGIA RECOMENDADA GEN-MAMA-MX — Flujo Automatizado de AlphaFold3
A14: PASO 1 | B14: Consultar AlphaFold DB (EMBL-EBI) para proteínas WT | C14: GET https://alphafold.ebi.ac.uk/api/prediction/{UniProt_ID} Descarga automática PDB/mmCIF. Script Python: requests + UniProt ID de fetch_fasta.py. Si estructura WT existe en DB → DESCARGAR GRATIS. Si no → usar AF3 self-hosted. | D14: $0 | E14: 15 genes × única vez → caché en GCS
A15: PASO 2 | B15: Batch JSON upload al AlphaFold Server (proteínas nuevas WT no en DB) | C15: Generar JSON batch con hasta 100 jobs. Subir vía alphafoldserver.com UI. 30 jobs/día. Para 15 genes WT → 1 día de procesamiento (solo primera vez). Resultados: ZIP con CIF + fold_<name>_job_request.json (reproducible). | D15: $0 (30 jobs/día) | E15: 30 jobs/día → ~15 genes WT en 1 día
A16: PASO 3 | B16: AF3 Self-Hosted en GCP (VM a2-highgpu-1g) — Proteínas MUTADAS batch | C16: VM GCP a2-highgpu-1g: A100 40GB, 12 vCPUs, 85GB RAM. Docker container. Pipeline: top_variants.json → generar JSON AF3 → run_alphafold.py --json_path batch. Output GCS: gs://gemamx-gold/alphafold3/mutadas/{variante}_{cambio}/ Start/Stop automático con Vertex AI Pipelines: solo paga cuando corre. | D16: $3.67/hr × 8hr/día → $29.4/día → $0.47/pred | E16: ~56 preds/día/VM (A100 40GB @ 8min/pred)
A17: PASO 4 | B17: AlphaFast (Modal serverless) — Escala masiva Año 2-3 | C17: Modal.com: infraestructura serverless con H200 GPUs. Script: pip install modal && modal run alphafast_gemamx.py Batch: 15 genes × variantes missense por muestra. Facturación por segundo. Pesos AF3 almacenados en Modal Volume (persistente entre runs). | D17: $0.035/pred (H200 serverless) | E17: 28 seg/pred → 3,086 preds/día × $0.035 = $108/día
A18: PASO 5 | B18: Almacenamiento y caché en GCS — Bronze/Silver/Gold | C18: Bronze: raw ZIP de AF Server + JSON inputs → gs://gemamx-bronze/alphafold3/ Silver: CIF extraídos + metadata pLDDT → gs://gemamx-silver/structures/ Gold: estructuras validadas + manifest_structures.json → gs://gemamx-gold/structures/ scan_boltz.py (ya en pipeline) adaptado para AF3: scan_af3.py con glob CIF. Lifecycle: Bronze → Nearline 30 días, Silver → Standard, Gold → siempre Standard. | D18: ~$0.020/GB/mes (GCS Standard Gold) ~$0.010/GB Nearline | E18: ~5MB/estructura CIF 15 genes × 30K casos → ~2.25 TB/año Gold
A20: 💰 ESTIMACIÓN DE COSTOS AlphaFold3 por AÑO — GEN-MAMA-MX (30K casos/año meta)
A21: Componente | B21: Detalle del Costo | C21: Año 1 (9K casos) | D21: Año 2 (19.5K casos) | E21: Año 3 (30K casos) | F21: Notas
A22: AlphaFold DB — Descarga WT (API REST EMBL-EBI) | B22: 15 genes únicos × 1 descarga. API: alphafold.ebi.ac.uk/api/prediction/{UniProt_ID}. Datos CC-BY-4.0 gratuitos. Caché local en GCS-Standard → 0.020/GB × ~0.075GB = $0.0015/mes. | C22: $0 (descarga) + $0.01/mes GCS | D22: $0 (cacheado) | E22: $0 (cacheado) | F22: Gratis. Solo 15 genes × 1 PDB/CIF cada uno. Costo almacenamiento mínimo. UniProt IDs ya en fetch_fasta.py.
A23: AF Server (JSON batch) — WT nuevas / validación | B23: 30 jobs/día gratis. Año 1: ~15 nuevas predicciones WT (1 día). Año 2-3: reuso de caché. Posible registro de múltiples cuentas académicas UNISON/IMSS. | C23: $0 (30 jobs/día) | D23: $0 | E23: $0 | F23: Sin costo. Límite: 30 jobs/día. Multi-cuenta posible para investigadores. Alternativa para variantes complejas (proteína+ligando simultáneo).
A24: AF3 Self-Hosted GCP a2-highgpu-1g (A100 40GB) — Proteínas MUTADAS | B24: VM on-demand: $3.67/hr. Preemptible: $1.10/hr (70% descuento). 8 min/predicción → 7.5 preds/hr. Año1: 13,500 preds mutadas / 7.5 = 1,800 hrs GPU. Mix: 50% on-demand + 50% preemptible → $2.39/hr promedio. | C24: 13,500 preds × $0.32/pred (preemptible) = $4,320 | D24: 48,750 preds × $0.30/pred = $14,625 | E24: 105,000 preds × $0.28/pred = $29,400 | F24: Costos disminuyen Años 2-3 por: caché de variantes comunes, committed use discount (CUD 1 año = 37% off), y mayor % preemptible.
A25: AlphaFast (Modal) — Alto throughput Año 2-3 | B25: $0.035/pred serverless. H200 GPU. 28 seg/pred. Opción complementaria para lotes grandes cuando la VM AF3 está saturada. Requiere pesos AF3 y cuenta Modal (billing por segundo). | C25: $0 (no se usa Año 1) | D25: 10,000 preds batch × $0.035 = $350 | E25: 30,000 preds batch × $0.035 = $1,050 | F25: Se activa Año 2 para picos de demanda. Ahorro vs VM: $0.035 vs $0.30-0.47/pred (7-13× más barato por pred en volumen alto).
A26: GCS Storage — Estructuras AF3 CIF/PDB (Gold layer) | B26: ~5MB/estructura CIF. 15 genes × casos × variantes. Año1: 13,515 structs × 5MB = ~67.6GB. Año3: ~525GB. GCS Standard: $0.020/GB/mes. | C26: 67.6 GB × $0.020 = $1.35/mes = $16/año | D26: 237 GB × $0.020 = $4.74/mes = $57/año | E26: 525 GB × $0.020 = $10.50/mes = $126/año | F26: Bronze: ZIP originales → Nearline ($0.010/GB). Silver: CIF extraídos → Standard. Gold: final validados → Standard. Lifecycle rules en GCS reducen costo automáticamente.
A27: Egress — Descarga estructuras para investigadores | B27: Investigadores descargan CIF/PDB para análisis local PyMOL/ChimeraX. ~5MB/estructura × N descargas. Egress GCP: $0.08/GB. | C27: ~10GB/mes egress × $0.08 = $0.80/mes = $10/año | D27: ~30GB/mes = $2.40/mes = $29/año | E27: ~80GB/mes = $6.40/mes = $77/año | F27: CDN (Cloud CDN) puede reducir egress 60-70% para assets frecuentes. Estructuras WT son las más descargadas → candidatas a CDN.
A28: Administración y Setup AF3 self-hosted | B28: Tiempo de bioinformático para: solicitar pesos AF3 a Google, setup Docker container GCP, pipeline automation Nextflow/Vertex AI, scripts JSON generation, scan_af3.py, monitoring. | C28: 40 horas setup × $50/hr = $2,000 (costo único Año 1) | D28: $0 (amortizado) | E28: $0 (amortizado) | F28: Setup único. Incluye: request pesos Google (2-3 días hábiles), Docker build + test, pipeline JSON auto-generation desde top_variants.json, integración GCS output con scan_af3.py.
A29: TOTAL COSTO AlphaFold3 (AF3 self-hosted + AlphaFast + storage + egress) | C29: $6,346 / año | D29: $15,061 / año | E29: $30,653 / año | F29: Costo marginal por predicción mutada: Año1 $0.47 → Año3 $0.28 (por CUD + caché). WT: $0 usando DB. AlphaFast reduce a $0.035/pred para picos de volumen.
A31: ⚙️ CÓDIGO PYTHON — Automatización Completa AlphaFold3 para GEN-MAMA-MX
A32: PASO 1 — Consultar AlphaFold DB (WT gratis) | B32: import requests, json from pathlib import Path def fetch_wt_from_alphafolddb(uniprot_id: str, gene: str, out_dir: Path) -> str | None: """Descarga estructura WT de AlphaFold DB si existe. Retorna path CIF o None.""" url = f"https://alphafold.ebi.ac.uk/api/prediction/{uniprot_id}" resp = requests.get(url, timeout=30) if resp.status_code != 200: return None # No está en DB → usar AF3 self-hosted data = resp.json()[0] cif_url = data["cifUrl"] cif_resp = requests.get(cif_url, timeout=60) cif_path = out_dir / f"{gene}_WT_alphafolddb.cif" cif_path.write_bytes(cif_resp.content) plddt = data.get("confidenceScore", 0) print(f"✅ {gene} WT descargado de AlphaFold DB. pLDDT global: {plddt}") return str(cif_path) # Uso: UnIProt IDs ya disponibles en fetch_fasta.py del pipeline GENE_UNIPROT = {"PIK3CA": "P42336", "TP53": "P04637", "ERBB2": "P04626", "BRCA1": "P38398", "BRCA2": "P51587", "CDH1": "P12830", "GATA3": "P23771", "MAP3K1": "Q13233", "PTEN": "P60484", "KMT2C": "Q8NEZ4", "RB1": "P06400", "ARID1A": "O14497", "SF3B1": "O75533", "AKT1": "P31749", "CBFB": "Q13951"} out_dir = Path("data/structures/alphafolddb") out_dir.mkdir(parents=True, exist_ok=True) manifest_wt = {} for gene, uid in GENE_UNIPROT.items(): path = fetch_wt_from_alphafolddb(uid, gene, out_dir) manifest_wt[f"{gene}_WT"] = path # None si no está en DB
A33: PASO 2 — Generar JSON batch para AF3 self-hosted (mutadas) | B33: import json from pathlib import Path def load_top_variants(path="data/top_variants.json"): return json.loads(Path(path).read_text()) def generate_af3_json(gene: str, mutation: str, fasta_seq: str, out_dir: Path) -> Path: """Genera JSON AF3 para una variante mutada.""" name = f"{gene}_{mutation}" payload = { "name": name, "sequences": [{"protein": {"id": ["A"], "sequence": fasta_seq}}], "modelSeeds": [1, 2, 3], # 3 seeds para mayor precisión "dialect": "alphafold3", "version": 1 } json_path = out_dir / f"{name}_af3_input.json" json_path.write_text(json.dumps(payload, indent=2)) return json_path # Cargar FASTA mutados generados por fetch_fasta.py variants = load_top_variants() json_dir = Path("data/alphafold3_inputs") json_dir.mkdir(parents=True, exist_ok=True) for v in variants[:20]: # Top-20 variantes gene = v["hugo_symbol"] mutation = v["protein_change"] # Leer FASTA mutado generado por fetch_fasta.py fasta_path = Path(f"data/fasta/{gene}_{mutation}.fasta") if fasta_path.exists(): seq = "".join(fasta_path.read_text().split("\n")[1:]) # sin header generate_af3_json(gene, mutation, seq, json_dir) print(f"✅ JSON generado: {gene}_{mutation}")
A34: PASO 3 — Ejecutar AF3 self-hosted en GCP (batch automático) | B34: #!/bin/bash # run_af3_batch.sh — ejecutado en VM GCP a2-highgpu-1g via SSH # Iniciado automáticamente por Vertex AI Pipelines cuando hay nuevas variantes INPUT_DIR="/gcs/gemamx-bronze/alphafold3/inputs" OUTPUT_DIR="/gcs/gemamx-gold/alphafold3/mutadas" MODEL_DIR="/mnt/af3_weights" # Pesos AF3 en persistent disk DB_DIR="/mnt/af3_databases" # 1TB SSD bases de datos # Procesar todos los JSON del directorio input for json_file in ${INPUT_DIR}/*.json; do variant=$(basename $json_file _af3_input.json) out_path="${OUTPUT_DIR}/${variant}" if [ -d "$out_path" ]; then echo "⏭️ Cacheado: $variant" continue fi echo "🔬 Prediciendo: $variant" docker run --rm --gpus all \ --volume ${INPUT_DIR}:/root/af_input \ --volume ${OUTPUT_DIR}:/root/af_output \ --volume ${MODEL_DIR}:/root/models \ --volume ${DB_DIR}:/root/public_databases \ alphafold3 python run_alphafold.py \ --json_path=/root/af_input/$(basename $json_file) \ --model_dir=/root/models \ --output_dir=/root/af_output \ --num_diffusion_samples=5 \ --num_recycles=10 echo "✅ Completado: $variant → $out_path" done # Actualizar manifest en GCS python scan_af3.py --output_dir ${OUTPUT_DIR} gsutil cp manifest_structures_af3.json gs://gemamx-gold/alphafold3/manifest_structures.json echo "📋 Manifest actualizado"
A35: PASO 4 — Actualizar manifest y metadata en Delta Lake | B35: import glob, json from pathlib import Path from pyspark.sql import SparkSession from delta import DeltaTable def scan_af3_outputs(output_dir: str) -> dict: """Escanea outputs AF3 y actualiza manifest_structures.json.""" manifest = {} for cif_path in glob.glob(f"{output_dir}/**/model.cif", recursive=True): # Extraer variante del path: .../PIK3CA_H1047R/seed-1_sample-0/model.cif parts = Path(cif_path).parts variant = [p for p in parts if "_" in p and any(c.isupper() for c in p)][0] # Leer pLDDT del JSON de confianza conf_glob = str(Path(cif_path).parent / "confidence_*.json") conf_files = glob.glob(conf_glob) plddt = 0.0 if conf_files: conf = json.loads(Path(conf_files[0]).read_text()) plddt = round(conf.get("complex_plddt", 0) * 100, 1) manifest[variant] = {"path": cif_path, "plddt": plddt, "source": "alphafold3"} return manifest # Actualizar Delta Gold table con nuevas estructuras spark = SparkSession.builder.appName("AF3Manifest").getOrCreate() manifest = scan_af3_outputs("gs://gemamx-gold/alphafold3/mutadas") # Escribir manifest JSON para compatibilidad con structural.js existente Path("manifest_structures.json").write_text(json.dumps(manifest, indent=2)) # También actualizar tabla Delta Silver con métricas pLDDT rows = [{"variant_id": k, "plddt": v["plddt"], "source": "AF3", "path_gcs": v["path"]} for k, v in manifest.items()] df = spark.createDataFrame(rows) df.write.format("delta").mode("overwrite").save("gs://gemamx-gold/delta/structures") print(f"✅ {len(manifest)} estructuras AF3 indexadas en Delta Gold")
A37: 📜 TÉRMINOS DE USO AlphaFold3 — IMPORTANTE para GEN-MAMA-MX / UNISON
A38: Modalidad | B38: Licencia | C38: Aplicabilidad para GEN-MAMA-MX / UNISON | D38: Consideraciones Importantes | E38: Consideraciones Importantes
A39: AlphaFold Server (alphafoldserver.com) | B39: Uso académico NO-COMERCIAL gratuito. CC-BY-NC-SA 4.0. | C39: ✅ APTO — UNISON es institución académica. IMSS: revisar términos si se considera prestación de servicio clínico pagado. | D39: ⚠️ Si el pipeline GEN-MAMA-MX se monetiza o presta servicios pagados, este modo NO es válido. Usar AF3 self-hosted con pesos académicos.
A40: AF3 Self-Hosted (Pesos Google) | B40: Solo para investigadores afiliados a organizaciones NO-comerciales. Formulario Google para solicitar pesos. Aprobación en 2-3 días hábiles. | C40: ✅ APTO — UNISON, INMEGEN, INCan aplican. Investigadores deben solicitar individualmente o vía institución. | D40: ⚠️ No se pueden redistribuir los pesos del modelo. No se puede usar para generar estructuras para clientes comerciales farmacéuticos.
A41: AlphaFold DB (EMBL-EBI) | B41: CC-BY-4.0 — Uso académico Y comercial. Sin restricciones de uso. | C41: ✅ APTO para cualquier uso — académico, clínico, comercial. Solo estructuras WT pre-calculadas. | D41: ✅ Sin restricciones. Citar: Fleming J. et al. Journal of Molecular Biology (2025).
A42: AlphaFast (RomeroLab/Modal) | B42: MIT License (código). Requiere pesos AF3 propios de Google (mismas restricciones que AF3 self-hosted). | C42: ✅ APTO si ya se tienen pesos AF3 aprobados. Modal (proveedor cloud) factura por segundo. | D42: ⚠️ Los pesos AF3 aplican las mismas restricciones de uso no-comercial.
A43: ColabFold / AlphaFold2 | B43: Uso libre (Apache 2.0 código). Modelos MIT. Sin restricciones significativas. | C43: ✅ APTO sin restricciones. AlphaFold2 completamente open. Menor precisión que AF3. | D43: ✅ Útil como fallback. Para prototipado sin necesidad de aprobación Google.
A45: 🔗 INTEGRACIÓN AF3 CON PIPELINE GEMAMX EXISTENTE — Cambios al Código
A46: generate_structures.py | B46: ACTUAL: Usa ESMFold API (HTTP) + Boltz-1 (Colab T4). NUEVO: Paso 0 → consultar AlphaFold DB. Si existe → usar. Si no → llamar AF3 self-hosted via SSH o AlphaFast Modal. Función fetch_wt_from_alphafolddb() ya diseñada arriba. | E46: Modificación MEDIA — ~50 líneas adicionales
A47: scan_boltz.py → scan_af3.py | B47: ACTUAL: Escanea boltz_results_*/ para CIF + confidence JSON. NUEVO: scan_af3.py escanea estructura AF3 diferente: af3_output/{variante}/seed-1_sample-0/model.cif af3_output/{variante}/seed-1_sample-0/confidences.json → complex_plddt manifest_structures.json compatible — misma estructura. | E47: Modificación BAJA — ~30 líneas
A48: structural.js (App Web) | B48: SIN CAMBIOS — PDBe Molstar ya soporta mmCIF de AF3. Los CIF de AF3 son mmCIF estándar, idénticos en estructura a Boltz-1. manifest_structures.json formato idéntico → carga automática. | E48: Sin cambios necesarios
A49: Vertex AI Pipeline (nuevo componente) | B49: Agregar componente KFP: 'AF3_Batch_Predictor' Trigger: cuando nuevas variantes llegan a Silver Delta table Steps: start GCP VM → copy JSONs → run docker AF3 → copy CIF a GCS → scan_af3.py → update manifest Stop VM al terminar (ahorro costo). | E49: Desarrollo NUEVO — ~4 horas bioinformático
A50: Databricks ML Pipeline (registro modelos) | B50: AF3 produce pLDDT por residuo (columna BISO en CIF). Nuevo feature para clasificador VUS: pLDDT_AF3 vs pLDDT_Boltz2. MLflow tracking: registrar fuente de estructura (AF3/Boltz/ESMFold). Delta Gold: campo 'structure_source' = 'alphafolddb' | 'af3_selfhosted' | 'boltz2' | E50: Modificación BAJA — ~20 líneas

Sheet Supuestos y Benchmarks
A1: GEN-MAMA-MX — Supuestos, Benchmarks y Referencias de Precios
A2: Parámetro | B2: Valor / Descripción | C2: Fuente | D2: Notas
A3: ── ESCALA DEL PROYECTO
A4: Casos NGS Año 1 | B4: 9,000 (30% de 30K meta anual) | C4: GEN-MAMA-MX Propuesta | D4: Ramp gradual por integración centros
A5: Casos NGS Año 2 | B5: 19,500 (65% de 30K) | C5: GEN-MAMA-MX Propuesta | D5: 12 centros activos IMSS/ISSSTE/privados
A6: Casos NGS Año 3 | B6: 30,000 (100% meta anual) | C6: GEN-MAMA-MX Propuesta | D6: Plena capacidad. 20+ centros en MX+LATAM
A7: Genes analizados por muestra | B7: 15 genes (Tier 1+2+3) | C7: Arquitectura Pipeline Doc v1.0 | D7: PIK3CA, TP53, ERBB2, BRCA1/2, CDH1, GATA3...
A8: Fármacos evaluados por variante | B8: 11 (catálogo base) → 50+ (producción) | C8: ChEMBL API | D8: FDA aprobados + ensayos clínicos
A9: Usuarios totales | B9: 150 investigadores + 15 admin + 10 devs | C9: GEN-MAMA-MX Propuesta | D9: 5 por centro + investigadores LATAM
A10: ── PRECIOS GCP (us-central1, 2025)
A11: GPU T4 on-demand | B11: $1.40/hr (n1-standard-8 + T4) | C11: GCP Pricing 2025 | D11: Boltz-2: ~20 min/predicción = $0.47/sim
A12: GPU T4 preemptible | B12: $0.35/hr | C12: GCP Pricing 2025 | D12: 75% descuento. Para lotes docking no urgentes
A13: CPU e2-standard-8 | B13: $0.27/hr | C13: GCP Pricing 2025 | D13: Pipelines bioinformáticos generales
A14: n2-highcpu-32 | B14: $0.94/hr | C14: GCP Pricing 2025 | D14: NGS alignment GATK/BWA. Ref Franzoso 2025
A15: GCS Standard | B15: $0.020/GB/mes | C15: GCP Pricing 2025 | D15: Bronze Gold layer. FASTQ, CIF, PDBQT
A16: GCS Nearline | B16: $0.010/GB/mes | C16: GCP Pricing 2025 | D16: Silver layer. Acceso mensual
A17: GCS Archive | B17: $0.0012/GB/mes | C17: GCP Pricing 2025 | D17: Backups largo plazo. Recuperación $0.05/GB
A18: BigQuery Storage | B18: $0.020/GB/mes | C18: GCP Pricing 2025 | D18: Active storage. First 10GB/mes gratis
A19: BigQuery Queries | B19: $5.00/TB procesado | C19: GCP Pricing 2025 | D19: First 1TB/mes gratis
A20: ── BENCHMARKS CIENTÍFICOS
A21: WES por muestra (Illumina NovaSeq X) | B21: ~$300 USD total (seq + análisis) | C21: INMEGEN MX; Franzoso 2025 | D21: No incluido en cloud — costo laboratorio separado
A22: Boltz-1/2 por simulación | B22: $0.10 en Fovus HPC; $0.47 en GCP T4 | C22: Fovus 2025; cálculo propio | D22: 20 min × $1.40/hr = $0.47. A80 GPU más rápido
A23: Vina GPU docking | B23: $0.95/10,000 dockings | C23: Fovus 2025 | D23: 30K casos × 15 genes × 11 fármacos = 4.95M dockings/año → $470/año
A24: Boltz-2 vs FEP | B24: $0.0001 vs $100 por predicción | C24: Recursion/MIT 2025 | D24: Boltz-2 1,000× más rápido que FEP physics-based
A25: GATK WES pipeline CPU | B25: 2.5 CPU-hrs/muestra | C25: Franzoso 2025; benchmarks CGC | D25: n2-highcpu-32 @ $0.94/hr = $2.35/muestra
A26: Pipeline NGS completo (alineación+variantes) | B26: $50/muestra promedio (CGC platform) | C26: Cancer Genomics Cloud docs | D26: Buffer +30% recomendado para errores/re-runs
A27: ── PREBCIOS DATABRICKS on GCP
A28: DBU Jobs Compute | B28: $0.15/DBU | C28: Databricks Pricing 2025 | D28: ETL, procesamiento Delta tables
A29: DBU SQL Warehouse | B29: $0.22/DBU | C29: Databricks Pricing 2025 | D29: Consultas investigadores
A30: DBU All-Purpose | B30: $0.40/DBU | C30: Databricks Pricing 2025 | D30: Notebooks interactivos
A31: ── REFERENCIAS ACADÉMICAS
A32: Franzoso et al. 2025 | B32: NGS en GCP: benchmark Sentieon/Parabricks WES/WGS | C32: Clinical and Translational Science, Nov 2025 | D32: Recomienda 64-96 CPUs Sentieon; GPU+48-64GB Parabricks
A33: Genomics Core — H. Albert Einstein Brasil | B33: Pipeline NGS AWS (Fargate+Batch+SPOT) | C33: AWS Public Sector Symposium Brasília 2024 | D33: Genomics Core con Varstation/Varsomics. SPOT para reducir costos
A34: CGC Seven Bridges — NCI | B34: Multicloud para TCGA. $50/tarea NGS avg | C34: docs.cancergenomicscloud.org | D34: Hosts TCGA-BRCA. Buffer +30% recomendado
A35: Fovus HPC 2025 | B35: $0.10/Boltz-1 sim; Vina GPU $0.95/10K | C35: fovus.co/2025/03/03 | D35: Referencia clave para escala 30K casos/año
A36: Azure Databricks Genomics — 3Cloud | B36: Databricks + Glow + VariantSpark para genómica | C36: 3cloudsolutions.com 2024 | D36: Patrón Bronze/Silver/Gold para VCF processing
A37: PMC GWAS en GCP (Hail) | B37: Scalability GWAS 500K genomas en GCP/AWS | C37: PMC7534581 | D37: Hail/Spark cloud supera HPC on-premise en costo-efectividad
A38: ── AlPHAFOLD3 DeepMind
A39: AlphaFold Server — cuota diaria | B39: 30 jobs/día/cuenta (actualización Nov 2024) | C39: alphafoldserver.com/release-updates | D39: Gratis. Subió de 10→20→30. Soporta JSON batch de hasta 100 drafts.
A40: AlphaFold3 self-hosted GCP a2-highgpu-1g | B40: ~$3.67/hr on-demand; ~$1.10/hr preemptible. ~8 min/predicción | C40: GCP GPU Pricing + GitHub deepmind/alphafold3/docs/installation.md | D40: Requiere A100 80GB o superior (Compute Capability 8.0+). 1TB SSD bases de datos.
A41: AlphaFast serverless (Modal/H200) | B41: $0.035/predicción. 28 seg/pred en H200. 68.5× más rápido que AF3 estándar | C41: Perry et al. bioRxiv Feb 2026 — RomeroLab/alphafast | D41: Requiere pesos AF3 de Google (mismas restricciones). Serverless vía Modal.
A42: AlphaFold DB (EMBL-EBI) | B42: GRATIS. >200M estructuras. CC-BY-4.0. REST API. | C42: alphafold.ebi.ac.uk — Fleming J. et al. J Mol Biology 2025 | D42: API: GET /api/prediction/{UniProt_ID}. Incluye proteoma humano completo. Solo WT.
A43: AF3 licencia uso | B43: CC-BY-NC-SA 4.0 (código). Pesos: solo académico no-comercial. Aprobación Google. | C43: github.com/google-deepmind/alphafold3/WEIGHTS_TERMS_OF_USE.md | D43: UNISON/INMEGEN aplican. IMSS revisar si hay prestación de servicio pagado.

Sheet Pipelines Bioinformáticos
A1: GEN-MAMA-MX — Tipos de Pipelines Bioinformáticos Implementables
A2: Pipelines categorizados por fase del análisis genómico-estructural-farmacológico. Todos orquestados con Nextflow Tower + MLOps en Vertex AI + tracking MLflow en Databricks.
A3: Pipeline | B3: Descripción | C3: Herramientas | D3: Cómputo GCP | E3: Salida
A4: ── FASE 1: INGESTA Y PREPROCESAMIENTO NGS
A5: P1 — WES Ingesta & QC | B5: Descarga FASTQ desde INMEGEN/IMSS, FastQC, Trimmomatic, validación muestras | C5: Nextflow nf-core/sarek, FastQC, MultiQC | D5: n2-highcpu-32 · $0.94/hr · 2.5 hr/muestra | E5: FASTQ QC → Bronze GCS
A6: P2 — Alineación Genómica | B6: BWA-MEM2 alignment vs GRCh38, GATK MarkDuplicates, BQSR, métricas cobertura | C6: BWA-MEM2, GATK 4.4, Samtools, Picard | D6: n2-highcpu-64 · $1.88/hr · 1.5 hr/muestra | E6: BAM alineado → Bronze GCS
A7: P3 — Variant Calling | B7: GATK HaplotypeCaller (germinal) + Mutect2 (somático vs tejido normal), filtros PASS | C7: GATK 4.4, Strelka2, DKFZ/ODCF pipeline | D7: n2-highcpu-32 · 1 hr/muestra | E7: VCF somático filtrado → Bronze GCS
A8: ── FASE 2: ANOTACIÓN Y PRIORIZACIÓN
A9: P4 — Anotación Funcional | B9: Annovar/VEP: impacto funcional, ClinVar, OncoKB, COSMIC, gnomAD frecuencias | C9: GATK FUNCOTATOR, VEP, Annovar, snpEff | D9: e2-standard-8 · 0.5 hr/muestra | E9: VCF anotado → Silver Delta Lake
A10: P5 — Priorización Variantes | B10: Filtro genes Tier 1/2/3, ranking por frecuencia cohorte, clasificación VUS/Patogénica, integración top_variants.json | C10: Python/Pandas, Spark/Glow, cBioPortal API | D10: Databricks Jobs · 0.5 DBU/muestra | E10: top_variants.json → Silver/Gold Delta
A11: ── FASE 3: PREDICCIÓN ESTRUCTURAL IA
A12: P6 — Predicción Estructural WT | B12: AlphaFold3 Server (gratuito, 20 jobs/día académico) para proteínas WT, caché local en GCS para evitar re-cómputo | C12: AlphaFold 3, ColabFold batch | D12: A100 GPU · $3.67/hr · 30 min/proteína | E12: PDB/CIF WT → Gold GCS
A13: P7 — Predicción Estructural Mutada | B13: Boltz-2 (MIT License, sin límite jobs) para cada variante missense priorizada, extracción fragmento 360aa centrado en mutación | C13: Boltz-2, ESMFold API (backup <390aa) | D13: T4 GPU · $1.40/hr · 20 min/sim = $0.47/sim | E13: CIF mutado · pLDDT JSON → Gold GCS
A14: P8 — Análisis Conformacional | B14: RMSD global y en sitio activo (WT vs Mutada), superposición estructural, identificación binding pockets con fpocket | C14: BioPython RMSD, fpocket 3.0, PyMOL CLI | D14: e2-standard-4 · 0.1 hr/variante | E14: structural_metrics.json → Gold Delta
A15: ── FASE 4: DOCKING MOLECULAR
A16: P9 — Preparación Ligandos | B16: Descarga SDF ChEMBL, conversión SDF→PDBQT 3D, generación coordenadas 3D ETKDG, optimización MMFF, tipos AD4 con Meeko | C16: RDKit, Meeko, OpenBabel 3.1.1, ChEMBL API | D16: e2-standard-4 · CPU solo | E16: PDBQT ligandos → GCS prep/
A17: P10 — Docking Molecular (AutoDock Vina) | B17: Batch docking: 15 variantes × 11 fármacos por muestra, caja 25Å centrada en residuo mutado, exhaustividad 8, 5 poses | C17: AutoDock Vina 1.2.3, Vina GPU (batch) | D17: GPU T4 preemptible · $0.35/hr · Vina GPU $0.95/10K | E17: vina_affinities.json → Gold Delta
A18: P11 — DiffDock (Top variantes) | B18: DiffDock deep learning docking para top 3 variantes por RMSD · Validación cruzada con Vina · Mayor precisión en candidatos repositionables | C18: DiffDock 1.1, PyTorch | D18: A100 GPU · $3.67/hr · 2 hr/variante | E18: Poses DiffDock + scores → Gold
A19: ── FASE 5: ML / INFERENCIA
A20: P12 — Clasificación VUS → Patogénica | B20: Modelo ML (XGBoost/RF) entrenado en cohorte TCGA-BRCA para reclasificar VUS · Features: RMSD, pLDDT, Vina score, frecuencia cohorte, gnomAD | C20: Databricks MLflow, XGBoost, SHAP explainability | D20: Databricks Jobs · All-Purpose cluster | E20: Clasificación VUS → Gold · Modelo versioned
A21: P13 — Recomendación Farmacológica | B21: Pipeline RAG+LLM: contexto variante + docking scores → recomendación clínica · Gemini 1.5 Pro con RAG sobre OncoKB/ClinVar/FDA labels | C21: Gemini 1.5 Pro API, Vertex AI Vector Search, LangChain | D21: Vertex AI · $0.0125/1K tokens | E21: Reporte clínico PDF/HTML → Gold GCS
A22: ── FASE 6: REPORTES Y DISTRIBUCIÓN
A23: P14 — Generación Reporte por Variante | B23: Auto-generación reporte integrado: perfil genómico + estructuras 3D + ranking fármacos + candidatos repositionables + síntesis diagnóstica (Jinja2/WeasyPrint) | C23: Jinja2, WeasyPrint, Plotly export | D23: Cloud Run · $0 (escala a cero) | E23: HTML + PDF → Gold GCS · Descarga investigadores
A24: P15 — Distribución Multi-canal | B24: APIs para intranet IMSS/ISSSTE, app móvil iOS/Android, portal investigadores LATAM · Delta Sharing para investigadores externos sin mover datos | C24: FastAPI microservicios GKE, Delta Sharing, GraphQL | D24: GKE 3 nodos e2-standard-4 | E24: REST API + GraphQL · App móvil · Portal web
A25: ── MLOPS — GESTIÓN DE MODELOS
A26: MLOps — Vertex AI Pipelines | B26: Kubeflow Pipelines para orquestar P6-P13 · Triggers automáticos por nuevos datos NGS · Retraining mensual con datos acumulados | C26: Vertex AI Pipelines, Kubeflow, Argo Workflows | D26: Vertex AI · $0.03/vCPU-hr | E26: Modelos versionados · Alertas drift
A27: MLOps — MLflow Tracking | B27: Tracking automático en Databricks: cada run de docking, cada predicción estructural, cada clasificación VUS · Reproducibilidad científica | C27: MLflow Managed (Databricks) | D27: Incluido en Databricks | E27: Experiment logs · Model registry
